{"id": "2748", "key": "Butler, Ohio, US", "data": [{"id": "0", "day": "01-01-2021", "confirmations": 25723, "deaths": 405, "recoveries": 0}, {"id": "1", "day": "01-02-2021", "confirmations": 26229, "deaths": 417, "recoveries": 0}, {"id": "2", "day": "01-03-2021", "confirmations": 26461, "deaths": 420, "recoveries": 0}, {"id": "3", "day": "01-04-2021", "confirmations": 26620, "deaths": 423, "recoveries": 0}, {"id": "4", "day": "01-05-2021", "confirmations": 26837, "deaths": 427, "recoveries": 0}, {"id": "5", "day": "01-06-2021", "confirmations": 27064, "deaths": 431, "recoveries": 0}, {"id": "6", "day": "01-07-2021", "confirmations": 27360, "deaths": 433, "recoveries": 0}, {"id": "7", "day": "01-08-2021", "confirmations": 27664, "deaths": 435, "recoveries": 0}, {"id": "8", "day": "01-09-2021", "confirmations": 27909, "deaths": 441, "recoveries": 0}, {"id": "9", "day": "01-10-2021", "confirmations": 28128, "deaths": 445, "recoveries": 0}, {"id": "10", "day": "01-11-2021", "confirmations": 28349, "deaths": 448, "recoveries": 0}, {"id": "11", "day": "01-12-2021", "confirmations": 28643, "deaths": 451, "recoveries": 0}, {"id": "12", "day": "01-13-2021", "confirmations": 28865, "deaths": 455, "recoveries": 0}, {"id": "13", "day": "01-14-2021", "confirmations": 29100, "deaths": 457, "recoveries": 0}, {"id": "14", "day": "01-15-2021", "confirmations": 29296, "deaths": 460, "recoveries": 0}, {"id": "15", "day": "01-16-2021", "confirmations": 29513, "deaths": 465, "recoveries": 0}, {"id": "16", "day": "01-17-2021", "confirmations": 29721, "deaths": 466, "recoveries": 0}, {"id": "17", "day": "01-18-2021", "confirmations": 29859, "deaths": 472, "recoveries": 0}, {"id": "18", "day": "01-19-2021", "confirmations": 30003, "deaths": 476, "recoveries": 0}, {"id": "19", "day": "01-20-2021", "confirmations": 30216, "deaths": 480, "recoveries": 0}, {"id": "20", "day": "01-21-2021", "confirmations": 30546, "deaths": 482, "recoveries": 0}, {"id": "21", "day": "01-22-2021", "confirmations": 30735, "deaths": 487, "recoveries": 0}, {"id": "22", "day": "01-23-2021", "confirmations": 30973, "deaths": 494, "recoveries": 0}, {"id": "23", "day": "01-24-2021", "confirmations": 31128, "deaths": 499, "recoveries": 0}, {"id": "24", "day": "01-25-2021", "confirmations": 31268, "deaths": 500, "recoveries": 0}, {"id": "25", "day": "01-26-2021", "confirmations": 31451, "deaths": 503, "recoveries": 0}, {"id": "26", "day": "01-27-2021", "confirmations": 31640, "deaths": 504, "recoveries": 0}, {"id": "27", "day": "01-28-2021", "confirmations": 31815, "deaths": 508, "recoveries": 0}, {"id": "28", "day": "01-29-2021", "confirmations": 32035, "deaths": 512, "recoveries": 0}, {"id": "29", "day": "01-30-2021", "confirmations": 32192, "deaths": 513, "recoveries": 0}, {"id": "30", "day": "01-31-2021", "confirmations": 32348, "deaths": 515, "recoveries": 0}, {"id": "31", "day": "02-01-2021", "confirmations": 32470, "deaths": 517, "recoveries": 0}, {"id": "32", "day": "02-02-2021", "confirmations": 32614, "deaths": 519, "recoveries": 0}, {"id": "33", "day": "02-03-2021", "confirmations": 32764, "deaths": 521, "recoveries": 0}, {"id": "34", "day": "02-04-2021", "confirmations": 32921, "deaths": 525, "recoveries": 0}, {"id": "35", "day": "02-05-2021", "confirmations": 33104, "deaths": 526, "recoveries": 0}, {"id": "36", "day": "02-06-2021", "confirmations": 33307, "deaths": 528, "recoveries": 0}, {"id": "37", "day": "02-07-2021", "confirmations": 33400, "deaths": 530, "recoveries": 0}, {"id": "38", "day": "02-08-2021", "confirmations": 33467, "deaths": 536, "recoveries": 0}, {"id": "39", "day": "02-09-2021", "confirmations": 33597, "deaths": 536, "recoveries": 0}, {"id": "40", "day": "02-10-2021", "confirmations": 33750, "deaths": 537, "recoveries": 0}, {"id": "41", "day": "02-11-2021", "confirmations": 33874, "deaths": 539, "recoveries": 0}, {"id": "42", "day": "02-12-2021", "confirmations": 34032, "deaths": 541, "recoveries": 0}, {"id": "43", "day": "02-13-2021", "confirmations": 34142, "deaths": 542, "recoveries": 0}, {"id": "44", "day": "02-14-2021", "confirmations": 34221, "deaths": 545, "recoveries": 0}, {"id": "45", "day": "02-15-2021", "confirmations": 34306, "deaths": 548, "recoveries": 0}, {"id": "46", "day": "02-16-2021", "confirmations": 34372, "deaths": 548, "recoveries": 0}, {"id": "47", "day": "02-17-2021", "confirmations": 34439, "deaths": 551, "recoveries": 0}, {"id": "48", "day": "02-18-2021", "confirmations": 34548, "deaths": 551, "recoveries": 0}, {"id": "49", "day": "02-19-2021", "confirmations": 34641, "deaths": 553, "recoveries": 0}, {"id": "50", "day": "02-20-2021", "confirmations": 34825, "deaths": 553, "recoveries": 0}, {"id": "51", "day": "02-21-2021", "confirmations": 34874, "deaths": 554, "recoveries": 0}, {"id": "52", "day": "02-22-2021", "confirmations": 34918, "deaths": 555, "recoveries": 0}, {"id": "53", "day": "02-23-2021", "confirmations": 35004, "deaths": 556, "recoveries": 0}, {"id": "54", "day": "02-24-2021", "confirmations": 35094, "deaths": 557, "recoveries": 0}, {"id": "55", "day": "02-25-2021", "confirmations": 35195, "deaths": 559, "recoveries": 0}, {"id": "56", "day": "02-26-2021", "confirmations": 35292, "deaths": 559, "recoveries": 0}, {"id": "57", "day": "02-27-2021", "confirmations": 35377, "deaths": 561, "recoveries": 0}, {"id": "58", "day": "02-28-2021", "confirmations": 35435, "deaths": 562, "recoveries": 0}, {"id": "59", "day": "03-01-2021", "confirmations": 35456, "deaths": 562, "recoveries": 0}, {"id": "60", "day": "03-02-2021", "confirmations": 35496, "deaths": 563, "recoveries": 0}, {"id": "61", "day": "03-03-2021", "confirmations": 35577, "deaths": 564, "recoveries": 0}, {"id": "62", "day": "03-04-2021", "confirmations": 35678, "deaths": 564, "recoveries": 0}, {"id": "63", "day": "03-05-2021", "confirmations": 35750, "deaths": 565, "recoveries": 0}, {"id": "64", "day": "03-06-2021", "confirmations": 35827, "deaths": 565, "recoveries": 0}, {"id": "65", "day": "03-07-2021", "confirmations": 35859, "deaths": 566, "recoveries": 0}, {"id": "66", "day": "03-08-2021", "confirmations": 35890, "deaths": 567, "recoveries": 0}, {"id": "67", "day": "03-09-2021", "confirmations": 35972, "deaths": 567, "recoveries": 0}, {"id": "68", "day": "03-10-2021", "confirmations": 36021, "deaths": 567, "recoveries": 0}, {"id": "69", "day": "03-11-2021", "confirmations": 36071, "deaths": 567, "recoveries": 0}, {"id": "70", "day": "03-12-2021", "confirmations": 36129, "deaths": 568, "recoveries": 0}, {"id": "71", "day": "03-13-2021", "confirmations": 36166, "deaths": 568, "recoveries": 0}, {"id": "72", "day": "03-14-2021", "confirmations": 36197, "deaths": 568, "recoveries": 0}, {"id": "73", "day": "03-15-2021", "confirmations": 36226, "deaths": 568, "recoveries": 0}, {"id": "74", "day": "03-16-2021", "confirmations": 36302, "deaths": 568, "recoveries": 0}, {"id": "75", "day": "03-17-2021", "confirmations": 36348, "deaths": 568, "recoveries": 0}, {"id": "76", "day": "03-18-2021", "confirmations": 36410, "deaths": 570, "recoveries": 0}, {"id": "77", "day": "03-19-2021", "confirmations": 36470, "deaths": 571, "recoveries": 0}, {"id": "78", "day": "03-20-2021", "confirmations": 36515, "deaths": 571, "recoveries": 0}, {"id": "79", "day": "03-21-2021", "confirmations": 36543, "deaths": 572, "recoveries": 0}, {"id": "80", "day": "03-22-2021", "confirmations": 36592, "deaths": 572, "recoveries": 0}, {"id": "81", "day": "03-23-2021", "confirmations": 36647, "deaths": 572, "recoveries": 0}, {"id": "82", "day": "03-24-2021", "confirmations": 36701, "deaths": 572, "recoveries": 0}, {"id": "83", "day": "03-25-2021", "confirmations": 36743, "deaths": 574, "recoveries": 0}, {"id": "84", "day": "03-26-2021", "confirmations": 36824, "deaths": 575, "recoveries": 0}, {"id": "85", "day": "03-27-2021", "confirmations": 36850, "deaths": 575, "recoveries": 0}, {"id": "86", "day": "03-28-2021", "confirmations": 36874, "deaths": 576, "recoveries": 0}, {"id": "87", "day": "03-29-2021", "confirmations": 36900, "deaths": 577, "recoveries": 0}, {"id": "88", "day": "03-30-2021", "confirmations": 36955, "deaths": 578, "recoveries": 0}, {"id": "89", "day": "03-31-2021", "confirmations": 36990, "deaths": 580, "recoveries": 0}, {"id": "90", "day": "04-01-2021", "confirmations": 37044, "deaths": 580, "recoveries": 0}, {"id": "91", "day": "04-02-2021", "confirmations": 37072, "deaths": 581, "recoveries": 0}, {"id": "92", "day": "04-03-2021", "confirmations": 37119, "deaths": 581, "recoveries": 0}, {"id": "93", "day": "04-04-2021", "confirmations": 37119, "deaths": 581, "recoveries": 0}, {"id": "94", "day": "04-05-2021", "confirmations": 37179, "deaths": 582, "recoveries": 0}, {"id": "95", "day": "04-06-2021", "confirmations": 37227, "deaths": 582, "recoveries": 0}, {"id": "96", "day": "04-07-2021", "confirmations": 37293, "deaths": 584, "recoveries": 0}, {"id": "97", "day": "04-08-2021", "confirmations": 37354, "deaths": 586, "recoveries": 0}, {"id": "98", "day": "04-09-2021", "confirmations": 37392, "deaths": 586, "recoveries": 0}, {"id": "99", "day": "04-10-2021", "confirmations": 37437, "deaths": 586, "recoveries": 0}, {"id": "100", "day": "04-11-2021", "confirmations": 37466, "deaths": 586, "recoveries": 0}, {"id": "101", "day": "04-12-2021", "confirmations": 37497, "deaths": 586, "recoveries": 0}, {"id": "102", "day": "04-13-2021", "confirmations": 37543, "deaths": 587, "recoveries": 0}, {"id": "103", "day": "04-14-2021", "confirmations": 37582, "deaths": 589, "recoveries": 0}, {"id": "104", "day": "04-15-2021", "confirmations": 37638, "deaths": 590, "recoveries": 0}, {"id": "105", "day": "04-16-2021", "confirmations": 37678, "deaths": 590, "recoveries": 0}, {"id": "106", "day": "04-17-2021", "confirmations": 37721, "deaths": 591, "recoveries": 0}, {"id": "107", "day": "04-18-2021", "confirmations": 37740, "deaths": 592, "recoveries": 0}, {"id": "108", "day": "04-19-2021", "confirmations": 37768, "deaths": 593, "recoveries": 0}, {"id": "109", "day": "04-20-2021", "confirmations": 37809, "deaths": 593, "recoveries": 0}, {"id": "110", "day": "04-21-2021", "confirmations": 37858, "deaths": 593, "recoveries": 0}, {"id": "111", "day": "04-22-2021", "confirmations": 37904, "deaths": 593, "recoveries": 0}, {"id": "112", "day": "04-23-2021", "confirmations": 37939, "deaths": 594, "recoveries": 0}, {"id": "113", "day": "04-24-2021", "confirmations": 37968, "deaths": 595, "recoveries": 0}, {"id": "114", "day": "04-25-2021", "confirmations": 37994, "deaths": 595, "recoveries": 0}, {"id": "115", "day": "04-26-2021", "confirmations": 38009, "deaths": 596, "recoveries": 0}, {"id": "116", "day": "04-27-2021", "confirmations": 38039, "deaths": 596, "recoveries": 0}, {"id": "117", "day": "04-28-2021", "confirmations": 38063, "deaths": 596, "recoveries": 0}, {"id": "118", "day": "04-29-2021", "confirmations": 38103, "deaths": 596, "recoveries": 0}, {"id": "119", "day": "04-30-2021", "confirmations": 38147, "deaths": 596, "recoveries": 0}, {"id": "120", "day": "05-01-2021", "confirmations": 38187, "deaths": 596, "recoveries": 0}, {"id": "121", "day": "05-02-2021", "confirmations": 38200, "deaths": 597, "recoveries": 0}, {"id": "122", "day": "05-03-2021", "confirmations": 38214, "deaths": 597, "recoveries": 0}, {"id": "123", "day": "05-04-2021", "confirmations": 38228, "deaths": 597, "recoveries": 0}, {"id": "124", "day": "05-05-2021", "confirmations": 38250, "deaths": 597, "recoveries": 0}, {"id": "125", "day": "05-06-2021", "confirmations": 38273, "deaths": 597, "recoveries": 0}, {"id": "126", "day": "05-07-2021", "confirmations": 38301, "deaths": 597, "recoveries": 0}, {"id": "127", "day": "05-08-2021", "confirmations": 38338, "deaths": 597, "recoveries": 0}, {"id": "128", "day": "05-09-2021", "confirmations": 38345, "deaths": 597, "recoveries": 0}, {"id": "129", "day": "05-10-2021", "confirmations": 38363, "deaths": 597, "recoveries": 0}, {"id": "130", "day": "05-11-2021", "confirmations": 38396, "deaths": 597, "recoveries": 0}, {"id": "131", "day": "05-12-2021", "confirmations": 38440, "deaths": 597, "recoveries": 0}, {"id": "132", "day": "05-13-2021", "confirmations": 38470, "deaths": 597, "recoveries": 0}, {"id": "133", "day": "05-14-2021", "confirmations": 38487, "deaths": 597, "recoveries": 0}, {"id": "134", "day": "05-15-2021", "confirmations": 38514, "deaths": 597, "recoveries": 0}, {"id": "135", "day": "05-16-2021", "confirmations": 38531, "deaths": 598, "recoveries": 0}, {"id": "136", "day": "05-17-2021", "confirmations": 38548, "deaths": 598, "recoveries": 0}, {"id": "137", "day": "05-18-2021", "confirmations": 38567, "deaths": 598, "recoveries": 0}, {"id": "138", "day": "05-19-2021", "confirmations": 38586, "deaths": 598, "recoveries": 0}, {"id": "139", "day": "05-20-2021", "confirmations": 38621, "deaths": 598, "recoveries": 0}, {"id": "140", "day": "05-21-2021", "confirmations": 38641, "deaths": 599, "recoveries": 0}, {"id": "141", "day": "05-22-2021", "confirmations": 38657, "deaths": 599, "recoveries": 0}, {"id": "142", "day": "05-23-2021", "confirmations": 38668, "deaths": 601, "recoveries": 0}, {"id": "143", "day": "05-24-2021", "confirmations": 38681, "deaths": 602, "recoveries": 0}, {"id": "144", "day": "05-25-2021", "confirmations": 38689, "deaths": 603, "recoveries": 0}, {"id": "145", "day": "05-26-2021", "confirmations": 38716, "deaths": 604, "recoveries": 0}, {"id": "146", "day": "05-27-2021", "confirmations": 38728, "deaths": 604, "recoveries": 0}, {"id": "147", "day": "05-28-2021", "confirmations": 38741, "deaths": 605, "recoveries": 0}, {"id": "148", "day": "05-29-2021", "confirmations": 38773, "deaths": 605, "recoveries": 0}, {"id": "149", "day": "05-30-2021", "confirmations": 38785, "deaths": 605, "recoveries": 0}, {"id": "150", "day": "05-31-2021", "confirmations": 38785, "deaths": 605, "recoveries": 0}, {"id": "151", "day": "06-01-2021", "confirmations": 38801, "deaths": 605, "recoveries": 0}, {"id": "152", "day": "06-02-2021", "confirmations": 38799, "deaths": 605, "recoveries": 0}, {"id": "153", "day": "06-03-2021", "confirmations": 38789, "deaths": 605, "recoveries": 0}, {"id": "154", "day": "06-04-2021", "confirmations": 38794, "deaths": 605, "recoveries": 0}, {"id": "155", "day": "06-05-2021", "confirmations": 38789, "deaths": 605, "recoveries": 0}, {"id": "156", "day": "06-06-2021", "confirmations": 38798, "deaths": 605, "recoveries": 0}, {"id": "157", "day": "06-07-2021", "confirmations": 38800, "deaths": 606, "recoveries": 0}, {"id": "158", "day": "06-08-2021", "confirmations": 38814, "deaths": 606, "recoveries": 0}, {"id": "159", "day": "06-09-2021", "confirmations": 38828, "deaths": 606, "recoveries": 0}, {"id": "160", "day": "06-10-2021", "confirmations": 38836, "deaths": 606, "recoveries": 0}, {"id": "161", "day": "06-11-2021", "confirmations": 38859, "deaths": 606, "recoveries": 0}, {"id": "162", "day": "06-12-2021", "confirmations": 38886, "deaths": 606, "recoveries": 0}, {"id": "163", "day": "06-13-2021", "confirmations": 38901, "deaths": 606, "recoveries": 0}, {"id": "164", "day": "06-14-2021", "confirmations": 38903, "deaths": 606, "recoveries": 0}, {"id": "165", "day": "06-15-2021", "confirmations": 38912, "deaths": 606, "recoveries": 0}, {"id": "166", "day": "06-16-2021", "confirmations": 38937, "deaths": 606, "recoveries": 0}, {"id": "167", "day": "06-17-2021", "confirmations": 38951, "deaths": 607, "recoveries": 0}, {"id": "168", "day": "06-18-2021", "confirmations": 39000, "deaths": 607, "recoveries": 0}, {"id": "169", "day": "06-19-2021", "confirmations": 39013, "deaths": 607, "recoveries": 0}, {"id": "170", "day": "06-20-2021", "confirmations": 39018, "deaths": 608, "recoveries": 0}, {"id": "171", "day": "06-21-2021", "confirmations": 39021, "deaths": 609, "recoveries": 0}, {"id": "172", "day": "06-22-2021", "confirmations": 39066, "deaths": 609, "recoveries": 0}, {"id": "173", "day": "06-23-2021", "confirmations": 39098, "deaths": 609, "recoveries": 0}, {"id": "174", "day": "06-24-2021", "confirmations": 39121, "deaths": 609, "recoveries": 0}, {"id": "175", "day": "06-25-2021", "confirmations": 39130, "deaths": 609, "recoveries": 0}, {"id": "176", "day": "06-26-2021", "confirmations": 39136, "deaths": 610, "recoveries": 0}, {"id": "177", "day": "06-27-2021", "confirmations": 39140, "deaths": 610, "recoveries": 0}, {"id": "178", "day": "06-28-2021", "confirmations": 39147, "deaths": 610, "recoveries": 0}, {"id": "179", "day": "06-29-2021", "confirmations": 39155, "deaths": 610, "recoveries": 0}, {"id": "180", "day": "06-30-2021", "confirmations": 39162, "deaths": 610, "recoveries": 0}, {"id": "181", "day": "07-01-2021", "confirmations": 39517, "deaths": 610, "recoveries": 0}, {"id": "182", "day": "07-02-2021", "confirmations": 39517, "deaths": 610, "recoveries": 0}, {"id": "183", "day": "07-03-2021", "confirmations": 39522, "deaths": 610, "recoveries": 0}, {"id": "184", "day": "07-04-2021", "confirmations": 39522, "deaths": 610, "recoveries": 0}, {"id": "185", "day": "07-05-2021", "confirmations": 39535, "deaths": 610, "recoveries": 0}, {"id": "186", "day": "07-06-2021", "confirmations": 39538, "deaths": 610, "recoveries": 0}, {"id": "187", "day": "07-07-2021", "confirmations": 39547, "deaths": 611, "recoveries": 0}, {"id": "188", "day": "07-08-2021", "confirmations": 39570, "deaths": 611, "recoveries": 0}, {"id": "189", "day": "07-09-2021", "confirmations": 39599, "deaths": 611, "recoveries": 0}, {"id": "190", "day": "07-10-2021", "confirmations": 39607, "deaths": 611, "recoveries": 0}, {"id": "191", "day": "07-11-2021", "confirmations": 39614, "deaths": 611, "recoveries": 0}, {"id": "192", "day": "07-12-2021", "confirmations": 39625, "deaths": 611, "recoveries": 0}, {"id": "193", "day": "07-13-2021", "confirmations": 39640, "deaths": 612, "recoveries": 0}, {"id": "194", "day": "07-14-2021", "confirmations": 39659, "deaths": 612, "recoveries": 0}, {"id": "195", "day": "07-15-2021", "confirmations": 39683, "deaths": 612, "recoveries": 0}, {"id": "196", "day": "07-16-2021", "confirmations": 39699, "deaths": 612, "recoveries": 0}, {"id": "197", "day": "07-17-2021", "confirmations": 39725, "deaths": 614, "recoveries": 0}, {"id": "198", "day": "07-18-2021", "confirmations": 39730, "deaths": 614, "recoveries": 0}, {"id": "199", "day": "07-19-2021", "confirmations": 39748, "deaths": 614, "recoveries": 0}, {"id": "200", "day": "07-20-2021", "confirmations": 39773, "deaths": 615, "recoveries": 0}, {"id": "201", "day": "07-21-2021", "confirmations": 39814, "deaths": 615, "recoveries": 0}, {"id": "202", "day": "07-22-2021", "confirmations": 39845, "deaths": 615, "recoveries": 0}, {"id": "203", "day": "07-23-2021", "confirmations": 39879, "deaths": 615, "recoveries": 0}, {"id": "204", "day": "07-24-2021", "confirmations": 39902, "deaths": 615, "recoveries": 0}, {"id": "205", "day": "07-25-2021", "confirmations": 39925, "deaths": 615, "recoveries": 0}, {"id": "206", "day": "07-26-2021", "confirmations": 39936, "deaths": 615, "recoveries": 0}, {"id": "207", "day": "07-27-2021", "confirmations": 40000, "deaths": 615, "recoveries": 0}, {"id": "208", "day": "07-28-2021", "confirmations": 40064, "deaths": 615, "recoveries": 0}, {"id": "209", "day": "07-29-2021", "confirmations": 40110, "deaths": 616, "recoveries": 0}, {"id": "210", "day": "07-30-2021", "confirmations": 40156, "deaths": 616, "recoveries": 0}, {"id": "211", "day": "07-31-2021", "confirmations": 40210, "deaths": 617, "recoveries": 0}, {"id": "212", "day": "08-01-2021", "confirmations": 40244, "deaths": 618, "recoveries": 0}, {"id": "213", "day": "08-02-2021", "confirmations": 40267, "deaths": 618, "recoveries": 0}, {"id": "214", "day": "08-03-2021", "confirmations": 40324, "deaths": 619, "recoveries": 0}, {"id": "215", "day": "08-04-2021", "confirmations": 40387, "deaths": 619, "recoveries": 0}, {"id": "216", "day": "08-05-2021", "confirmations": 40470, "deaths": 620, "recoveries": 0}, {"id": "217", "day": "08-06-2021", "confirmations": 40508, "deaths": 620, "recoveries": 0}, {"id": "218", "day": "08-07-2021", "confirmations": 40584, "deaths": 620, "recoveries": 0}, {"id": "219", "day": "08-08-2021", "confirmations": 40624, "deaths": 621, "recoveries": 0}, {"id": "220", "day": "08-09-2021", "confirmations": 40660, "deaths": 623, "recoveries": 0}, {"id": "221", "day": "08-10-2021", "confirmations": 40731, "deaths": 625, "recoveries": 0}, {"id": "222", "day": "08-11-2021", "confirmations": 40829, "deaths": 625, "recoveries": 0}, {"id": "223", "day": "08-12-2021", "confirmations": 40917, "deaths": 626, "recoveries": 0}, {"id": "224", "day": "08-13-2021", "confirmations": 40997, "deaths": 628, "recoveries": 0}, {"id": "225", "day": "08-14-2021", "confirmations": 41065, "deaths": 631, "recoveries": 0}, {"id": "226", "day": "08-15-2021", "confirmations": 41134, "deaths": 632, "recoveries": 0}, {"id": "227", "day": "08-16-2021", "confirmations": 41191, "deaths": 635, "recoveries": 0}, {"id": "228", "day": "08-17-2021", "confirmations": 41269, "deaths": 639, "recoveries": 0}, {"id": "229", "day": "08-18-2021", "confirmations": 41375, "deaths": 642, "recoveries": 0}, {"id": "230", "day": "08-19-2021", "confirmations": 41476, "deaths": 642, "recoveries": 0}, {"id": "231", "day": "08-20-2021", "confirmations": 41579, "deaths": 644, "recoveries": 0}, {"id": "232", "day": "08-21-2021", "confirmations": 41662, "deaths": 644, "recoveries": 0}, {"id": "233", "day": "08-22-2021", "confirmations": 41730, "deaths": 644, "recoveries": 0}, {"id": "234", "day": "08-23-2021", "confirmations": 41813, "deaths": 646, "recoveries": 0}, {"id": "235", "day": "08-24-2021", "confirmations": 41925, "deaths": 648, "recoveries": 0}, {"id": "236", "day": "08-25-2021", "confirmations": 42033, "deaths": 648, "recoveries": 0}, {"id": "237", "day": "08-26-2021", "confirmations": 42223, "deaths": 649, "recoveries": 0}, {"id": "238", "day": "08-27-2021", "confirmations": 42362, "deaths": 650, "recoveries": 0}, {"id": "239", "day": "08-28-2021", "confirmations": 42521, "deaths": 650, "recoveries": 0}, {"id": "240", "day": "08-29-2021", "confirmations": 42641, "deaths": 650, "recoveries": 0}, {"id": "241", "day": "08-30-2021", "confirmations": 42712, "deaths": 650, "recoveries": 0}, {"id": "242", "day": "08-31-2021", "confirmations": 42931, "deaths": 651, "recoveries": 0}, {"id": "243", "day": "09-01-2021", "confirmations": 43269, "deaths": 651, "recoveries": 0}, {"id": "244", "day": "09-02-2021", "confirmations": 43504, "deaths": 652, "recoveries": 0}, {"id": "245", "day": "09-03-2021", "confirmations": 43676, "deaths": 654, "recoveries": 0}, {"id": "246", "day": "09-04-2021", "confirmations": 43876, "deaths": 657, "recoveries": 0}, {"id": "247", "day": "09-05-2021", "confirmations": 44101, "deaths": 659, "recoveries": 0}, {"id": "248", "day": "09-06-2021", "confirmations": 44184, "deaths": 661, "recoveries": 0}, {"id": "249", "day": "09-07-2021", "confirmations": 44349, "deaths": 661, "recoveries": 0}, {"id": "250", "day": "09-08-2021", "confirmations": 44499, "deaths": 663, "recoveries": 0}, {"id": "251", "day": "09-09-2021", "confirmations": 44687, "deaths": 667, "recoveries": 0}, {"id": "252", "day": "09-10-2021", "confirmations": 44994, "deaths": 669, "recoveries": 0}, {"id": "253", "day": "09-11-2021", "confirmations": 45265, "deaths": 670, "recoveries": 0}, {"id": "254", "day": "09-12-2021", "confirmations": 45363, "deaths": 673, "recoveries": 0}, {"id": "255", "day": "09-13-2021", "confirmations": 45521, "deaths": 673, "recoveries": 0}, {"id": "256", "day": "09-14-2021", "confirmations": 45737, "deaths": 673, "recoveries": 0}, {"id": "257", "day": "09-15-2021", "confirmations": 45993, "deaths": 677, "recoveries": 0}, {"id": "258", "day": "09-16-2021", "confirmations": 46214, "deaths": 679, "recoveries": 0}, {"id": "259", "day": "09-17-2021", "confirmations": 46471, "deaths": 679, "recoveries": 0}, {"id": "260", "day": "09-18-2021", "confirmations": 46732, "deaths": 681, "recoveries": 0}, {"id": "261", "day": "09-19-2021", "confirmations": 46869, "deaths": 682, "recoveries": 0}, {"id": "262", "day": "09-20-2021", "confirmations": 47000, "deaths": 686, "recoveries": 0}, {"id": "263", "day": "09-21-2021", "confirmations": 47209, "deaths": 688, "recoveries": 0}, {"id": "264", "day": "09-22-2021", "confirmations": 47417, "deaths": 689, "recoveries": 0}, {"id": "265", "day": "09-23-2021", "confirmations": 47623, "deaths": 691, "recoveries": 0}, {"id": "266", "day": "09-24-2021", "confirmations": 47858, "deaths": 691, "recoveries": 0}, {"id": "267", "day": "09-25-2021", "confirmations": 48000, "deaths": 695, "recoveries": 0}, {"id": "268", "day": "09-26-2021", "confirmations": 48139, "deaths": 698, "recoveries": 0}, {"id": "269", "day": "09-27-2021", "confirmations": 48223, "deaths": 702, "recoveries": 0}, {"id": "270", "day": "09-28-2021", "confirmations": 48427, "deaths": 705, "recoveries": 0}, {"id": "271", "day": "09-29-2021", "confirmations": 48587, "deaths": 707, "recoveries": 0}, {"id": "272", "day": "09-30-2021", "confirmations": 48783, "deaths": 710, "recoveries": 0}, {"id": "273", "day": "10-01-2021", "confirmations": 48916, "deaths": 712, "recoveries": 0}, {"id": "274", "day": "10-02-2021", "confirmations": 49095, "deaths": 715, "recoveries": 0}, {"id": "275", "day": "10-03-2021", "confirmations": 49189, "deaths": 718, "recoveries": 0}, {"id": "276", "day": "10-04-2021", "confirmations": 49303, "deaths": 719, "recoveries": 0}, {"id": "277", "day": "10-05-2021", "confirmations": 49446, "deaths": 720, "recoveries": 0}, {"id": "278", "day": "10-06-2021", "confirmations": 49586, "deaths": 723, "recoveries": 0}, {"id": "279", "day": "10-07-2021", "confirmations": 49745, "deaths": 726, "recoveries": 0}, {"id": "280", "day": "10-08-2021", "confirmations": 49919, "deaths": 728, "recoveries": 0}, {"id": "281", "day": "10-09-2021", "confirmations": 50048, "deaths": 730, "recoveries": 0}, {"id": "282", "day": "10-10-2021", "confirmations": 50195, "deaths": 736, "recoveries": 0}, {"id": "283", "day": "10-11-2021", "confirmations": 50272, "deaths": 739, "recoveries": 0}, {"id": "284", "day": "10-12-2021", "confirmations": 50387, "deaths": 739, "recoveries": 0}, {"id": "285", "day": "10-13-2021", "confirmations": 50526, "deaths": 741, "recoveries": 0}, {"id": "286", "day": "10-14-2021", "confirmations": 50677, "deaths": 743, "recoveries": 0}, {"id": "287", "day": "10-15-2021", "confirmations": 50803, "deaths": 747, "recoveries": 0}, {"id": "288", "day": "10-16-2021", "confirmations": 50923, "deaths": 752, "recoveries": 0}, {"id": "289", "day": "10-17-2021", "confirmations": 51008, "deaths": 754, "recoveries": 0}, {"id": "290", "day": "10-18-2021", "confirmations": 51076, "deaths": 759, "recoveries": 0}, {"id": "291", "day": "10-19-2021", "confirmations": 51168, "deaths": 763, "recoveries": 0}, {"id": "292", "day": "10-20-2021", "confirmations": 51309, "deaths": 766, "recoveries": 0}, {"id": "293", "day": "10-21-2021", "confirmations": 51383, "deaths": 768, "recoveries": 0}, {"id": "294", "day": "10-22-2021", "confirmations": 51500, "deaths": 771, "recoveries": 0}, {"id": "295", "day": "10-23-2021", "confirmations": 51580, "deaths": 773, "recoveries": 0}, {"id": "296", "day": "10-24-2021", "confirmations": 51659, "deaths": 774, "recoveries": 0}, {"id": "297", "day": "10-25-2021", "confirmations": 51696, "deaths": 775, "recoveries": 0}, {"id": "298", "day": "10-26-2021", "confirmations": 51809, "deaths": 778, "recoveries": 0}, {"id": "299", "day": "10-27-2021", "confirmations": 51893, "deaths": 778, "recoveries": 0}, {"id": "300", "day": "10-28-2021", "confirmations": 52002, "deaths": 780, "recoveries": 0}, {"id": "301", "day": "10-29-2021", "confirmations": 52114, "deaths": 782, "recoveries": 0}, {"id": "302", "day": "10-30-2021", "confirmations": 52220, "deaths": 785, "recoveries": 0}, {"id": "303", "day": "10-31-2021", "confirmations": 52295, "deaths": 787, "recoveries": 0}, {"id": "304", "day": "11-01-2021", "confirmations": 52347, "deaths": 790, "recoveries": 0}, {"id": "305", "day": "11-02-2021", "confirmations": 52483, "deaths": 790, "recoveries": 0}, {"id": "306", "day": "11-03-2021", "confirmations": 52585, "deaths": 793, "recoveries": 0}, {"id": "307", "day": "11-04-2021", "confirmations": 52698, "deaths": 797, "recoveries": 0}, {"id": "308", "day": "11-05-2021", "confirmations": 52796, "deaths": 797, "recoveries": 0}, {"id": "309", "day": "11-06-2021", "confirmations": 52879, "deaths": 800, "recoveries": 0}, {"id": "310", "day": "11-07-2021", "confirmations": 53002, "deaths": 800, "recoveries": 0}, {"id": "311", "day": "11-08-2021", "confirmations": 53041, "deaths": 802, "recoveries": 0}, {"id": "312", "day": "11-09-2021", "confirmations": 53145, "deaths": 802, "recoveries": 0}, {"id": "313", "day": "11-10-2021", "confirmations": 53292, "deaths": 803, "recoveries": 0}, {"id": "314", "day": "11-11-2021", "confirmations": 53427, "deaths": 805, "recoveries": 0}, {"id": "315", "day": "11-12-2021", "confirmations": 53564, "deaths": 805, "recoveries": 0}, {"id": "316", "day": "11-13-2021", "confirmations": 53666, "deaths": 808, "recoveries": 0}, {"id": "317", "day": "11-14-2021", "confirmations": 53773, "deaths": 809, "recoveries": 0}, {"id": "318", "day": "11-15-2021", "confirmations": 53841, "deaths": 811, "recoveries": 0}, {"id": "319", "day": "11-16-2021", "confirmations": 54022, "deaths": 812, "recoveries": 0}, {"id": "320", "day": "11-17-2021", "confirmations": 54204, "deaths": 815, "recoveries": 0}, {"id": "321", "day": "11-18-2021", "confirmations": 54354, "deaths": 819, "recoveries": 0}, {"id": "322", "day": "11-19-2021", "confirmations": 54531, "deaths": 822, "recoveries": 0}, {"id": "323", "day": "11-20-2021", "confirmations": 54693, "deaths": 825, "recoveries": 0}, {"id": "324", "day": "11-21-2021", "confirmations": 54776, "deaths": 828, "recoveries": 0}, {"id": "325", "day": "11-22-2021", "confirmations": 54887, "deaths": 830, "recoveries": 0}, {"id": "326", "day": "11-23-2021", "confirmations": 55043, "deaths": 832, "recoveries": 0}, {"id": "327", "day": "11-24-2021", "confirmations": 55231, "deaths": 834, "recoveries": 0}, {"id": "328", "day": "11-25-2021", "confirmations": 55231, "deaths": 835, "recoveries": 0}, {"id": "329", "day": "11-26-2021", "confirmations": 55535, "deaths": 837, "recoveries": 0}, {"id": "330", "day": "11-27-2021", "confirmations": 55597, "deaths": 840, "recoveries": 0}, {"id": "331", "day": "11-28-2021", "confirmations": 55716, "deaths": 845, "recoveries": 0}, {"id": "332", "day": "11-29-2021", "confirmations": 55878, "deaths": 846, "recoveries": 0}, {"id": "333", "day": "11-30-2021", "confirmations": 56096, "deaths": 850, "recoveries": 0}, {"id": "334", "day": "12-01-2021", "confirmations": 56343, "deaths": 854, "recoveries": 0}, {"id": "335", "day": "12-02-2021", "confirmations": 56598, "deaths": 856, "recoveries": 0}, {"id": "336", "day": "12-03-2021", "confirmations": 56852, "deaths": 860, "recoveries": 0}, {"id": "337", "day": "12-04-2021", "confirmations": 57083, "deaths": 862, "recoveries": 0}, {"id": "338", "day": "12-05-2021", "confirmations": 57225, "deaths": 864, "recoveries": 0}, {"id": "339", "day": "12-06-2021", "confirmations": 57319, "deaths": 866, "recoveries": 0}, {"id": "340", "day": "12-07-2021", "confirmations": 57534, "deaths": 869, "recoveries": 0}, {"id": "341", "day": "12-08-2021", "confirmations": 57796, "deaths": 872, "recoveries": 0}, {"id": "342", "day": "12-09-2021", "confirmations": 58042, "deaths": 874, "recoveries": 0}, {"id": "343", "day": "12-10-2021", "confirmations": 58244, "deaths": 878, "recoveries": 0}, {"id": "344", "day": "12-11-2021", "confirmations": 58487, "deaths": 882, "recoveries": 0}, {"id": "345", "day": "12-12-2021", "confirmations": 58587, "deaths": 885, "recoveries": 0}, {"id": "346", "day": "12-13-2021", "confirmations": 58792, "deaths": 887, "recoveries": 0}, {"id": "347", "day": "12-14-2021", "confirmations": 59244, "deaths": 888, "recoveries": 0}, {"id": "348", "day": "12-15-2021", "confirmations": 59547, "deaths": 890, "recoveries": 0}, {"id": "349", "day": "12-16-2021", "confirmations": 59929, "deaths": 891, "recoveries": 0}, {"id": "350", "day": "12-17-2021", "confirmations": 60147, "deaths": 891, "recoveries": 0}, {"id": "351", "day": "12-18-2021", "confirmations": 60399, "deaths": 892, "recoveries": 0}, {"id": "352", "day": "12-19-2021", "confirmations": 60529, "deaths": 893, "recoveries": 0}, {"id": "353", "day": "12-20-2021", "confirmations": 60704, "deaths": 893, "recoveries": 0}, {"id": "354", "day": "12-21-2021", "confirmations": 60952, "deaths": 893, "recoveries": 0}, {"id": "355", "day": "12-22-2021", "confirmations": 61260, "deaths": 893, "recoveries": 0}, {"id": "356", "day": "12-23-2021", "confirmations": 61521, "deaths": 893, "recoveries": 0}, {"id": "357", "day": "12-24-2021", "confirmations": 61779, "deaths": 894, "recoveries": 0}, {"id": "358", "day": "12-25-2021", "confirmations": 61779, "deaths": 895, "recoveries": 0}, {"id": "359", "day": "12-26-2021", "confirmations": 62126, "deaths": 895, "recoveries": 0}, {"id": "360", "day": "12-27-2021", "confirmations": 62306, "deaths": 895, "recoveries": 0}, {"id": "361", "day": "12-28-2021", "confirmations": 62779, "deaths": 896, "recoveries": 0}, {"id": "362", "day": "12-29-2021", "confirmations": 63238, "deaths": 897, "recoveries": 0}, {"id": "363", "day": "12-30-2021", "confirmations": 63801, "deaths": 897, "recoveries": 0}, {"id": "364", "day": "12-31-2021", "confirmations": 64354, "deaths": 897, "recoveries": 0}, {"id": "365", "day": "01-01-2022", "confirmations": 64354, "deaths": 897, "recoveries": 0}, {"id": "366", "day": "01-02-2022", "confirmations": 65272, "deaths": 897, "recoveries": 0}, {"id": "367", "day": "01-03-2022", "confirmations": 65744, "deaths": 897, "recoveries": 0}, {"id": "368", "day": "01-04-2022", "confirmations": 66296, "deaths": 897, "recoveries": 0}, {"id": "369", "day": "01-05-2022", "confirmations": 66888, "deaths": 897, "recoveries": 0}, {"id": "370", "day": "01-06-2022", "confirmations": 67445, "deaths": 897, "recoveries": 0}, {"id": "371", "day": "01-07-2022", "confirmations": 68213, "deaths": 909, "recoveries": 0}, {"id": "372", "day": "01-08-2022", "confirmations": 68779, "deaths": 909, "recoveries": 0}, {"id": "373", "day": "01-09-2022", "confirmations": 69440, "deaths": 909, "recoveries": 0}]}