{"id": "378", "key": "Madagascar", "data": [{"id": "0", "day": "01-01-2021", "confirmations": 17714, "deaths": 261, "recoveries": 17228}, {"id": "1", "day": "01-02-2021", "confirmations": 17767, "deaths": 262, "recoveries": 17298}, {"id": "2", "day": "01-03-2021", "confirmations": 17767, "deaths": 262, "recoveries": 17298}, {"id": "3", "day": "01-04-2021", "confirmations": 17767, "deaths": 262, "recoveries": 17298}, {"id": "4", "day": "01-05-2021", "confirmations": 17767, "deaths": 262, "recoveries": 17298}, {"id": "5", "day": "01-06-2021", "confirmations": 17767, "deaths": 262, "recoveries": 17298}, {"id": "6", "day": "01-07-2021", "confirmations": 17767, "deaths": 262, "recoveries": 17298}, {"id": "7", "day": "01-08-2021", "confirmations": 17767, "deaths": 262, "recoveries": 17298}, {"id": "8", "day": "01-09-2021", "confirmations": 17767, "deaths": 262, "recoveries": 17298}, {"id": "9", "day": "01-10-2021", "confirmations": 18001, "deaths": 267, "recoveries": 17447}, {"id": "10", "day": "01-11-2021", "confirmations": 18001, "deaths": 267, "recoveries": 17447}, {"id": "11", "day": "01-12-2021", "confirmations": 18001, "deaths": 267, "recoveries": 17447}, {"id": "12", "day": "01-13-2021", "confirmations": 18001, "deaths": 267, "recoveries": 17447}, {"id": "13", "day": "01-14-2021", "confirmations": 18001, "deaths": 267, "recoveries": 17447}, {"id": "14", "day": "01-15-2021", "confirmations": 18001, "deaths": 267, "recoveries": 17447}, {"id": "15", "day": "01-16-2021", "confirmations": 18001, "deaths": 267, "recoveries": 17447}, {"id": "16", "day": "01-17-2021", "confirmations": 18301, "deaths": 273, "recoveries": 17609}, {"id": "17", "day": "01-18-2021", "confirmations": 18301, "deaths": 273, "recoveries": 17609}, {"id": "18", "day": "01-19-2021", "confirmations": 18301, "deaths": 273, "recoveries": 17609}, {"id": "19", "day": "01-20-2021", "confirmations": 18301, "deaths": 273, "recoveries": 17609}, {"id": "20", "day": "01-21-2021", "confirmations": 18301, "deaths": 273, "recoveries": 17609}, {"id": "21", "day": "01-22-2021", "confirmations": 18301, "deaths": 273, "recoveries": 17609}, {"id": "22", "day": "01-23-2021", "confirmations": 18301, "deaths": 273, "recoveries": 17609}, {"id": "23", "day": "01-24-2021", "confirmations": 18743, "deaths": 279, "recoveries": 17930}, {"id": "24", "day": "01-25-2021", "confirmations": 18743, "deaths": 279, "recoveries": 17930}, {"id": "25", "day": "01-26-2021", "confirmations": 18743, "deaths": 279, "recoveries": 17930}, {"id": "26", "day": "01-27-2021", "confirmations": 18743, "deaths": 279, "recoveries": 17930}, {"id": "27", "day": "01-28-2021", "confirmations": 18743, "deaths": 279, "recoveries": 17930}, {"id": "28", "day": "01-29-2021", "confirmations": 18743, "deaths": 279, "recoveries": 17930}, {"id": "29", "day": "01-30-2021", "confirmations": 18743, "deaths": 279, "recoveries": 17930}, {"id": "30", "day": "01-31-2021", "confirmations": 19065, "deaths": 281, "recoveries": 18215}, {"id": "31", "day": "02-01-2021", "confirmations": 19065, "deaths": 281, "recoveries": 18215}, {"id": "32", "day": "02-02-2021", "confirmations": 19065, "deaths": 281, "recoveries": 18215}, {"id": "33", "day": "02-03-2021", "confirmations": 19065, "deaths": 281, "recoveries": 18215}, {"id": "34", "day": "02-04-2021", "confirmations": 19065, "deaths": 281, "recoveries": 18215}, {"id": "35", "day": "02-05-2021", "confirmations": 19065, "deaths": 281, "recoveries": 18215}, {"id": "36", "day": "02-06-2021", "confirmations": 19065, "deaths": 281, "recoveries": 18215}, {"id": "37", "day": "02-07-2021", "confirmations": 19360, "deaths": 285, "recoveries": 18490}, {"id": "38", "day": "02-08-2021", "confirmations": 19360, "deaths": 285, "recoveries": 18490}, {"id": "39", "day": "02-09-2021", "confirmations": 19360, "deaths": 285, "recoveries": 18490}, {"id": "40", "day": "02-10-2021", "confirmations": 19360, "deaths": 285, "recoveries": 18490}, {"id": "41", "day": "02-11-2021", "confirmations": 19360, "deaths": 285, "recoveries": 18490}, {"id": "42", "day": "02-12-2021", "confirmations": 19360, "deaths": 285, "recoveries": 18490}, {"id": "43", "day": "02-13-2021", "confirmations": 19360, "deaths": 285, "recoveries": 18490}, {"id": "44", "day": "02-14-2021", "confirmations": 19598, "deaths": 292, "recoveries": 18915}, {"id": "45", "day": "02-15-2021", "confirmations": 19598, "deaths": 292, "recoveries": 18915}, {"id": "46", "day": "02-16-2021", "confirmations": 19598, "deaths": 292, "recoveries": 18915}, {"id": "47", "day": "02-17-2021", "confirmations": 19598, "deaths": 292, "recoveries": 18915}, {"id": "48", "day": "02-18-2021", "confirmations": 19598, "deaths": 292, "recoveries": 18915}, {"id": "49", "day": "02-19-2021", "confirmations": 19598, "deaths": 292, "recoveries": 18915}, {"id": "50", "day": "02-20-2021", "confirmations": 19598, "deaths": 292, "recoveries": 18915}, {"id": "51", "day": "02-21-2021", "confirmations": 19831, "deaths": 297, "recoveries": 19296}, {"id": "52", "day": "02-22-2021", "confirmations": 19831, "deaths": 297, "recoveries": 19296}, {"id": "53", "day": "02-23-2021", "confirmations": 19831, "deaths": 297, "recoveries": 19296}, {"id": "54", "day": "02-24-2021", "confirmations": 19831, "deaths": 297, "recoveries": 19296}, {"id": "55", "day": "02-25-2021", "confirmations": 19831, "deaths": 297, "recoveries": 19296}, {"id": "56", "day": "02-26-2021", "confirmations": 19831, "deaths": 297, "recoveries": 19296}, {"id": "57", "day": "02-27-2021", "confirmations": 19831, "deaths": 297, "recoveries": 19296}, {"id": "58", "day": "02-28-2021", "confirmations": 19831, "deaths": 297, "recoveries": 19296}, {"id": "59", "day": "03-01-2021", "confirmations": 19831, "deaths": 297, "recoveries": 19296}, {"id": "60", "day": "03-02-2021", "confirmations": 19831, "deaths": 297, "recoveries": 19296}, {"id": "61", "day": "03-03-2021", "confirmations": 19831, "deaths": 297, "recoveries": 19296}, {"id": "62", "day": "03-04-2021", "confirmations": 19831, "deaths": 297, "recoveries": 19296}, {"id": "63", "day": "03-05-2021", "confirmations": 19831, "deaths": 297, "recoveries": 19296}, {"id": "64", "day": "03-06-2021", "confirmations": 20155, "deaths": 300, "recoveries": 19543}, {"id": "65", "day": "03-07-2021", "confirmations": 20155, "deaths": 300, "recoveries": 19543}, {"id": "66", "day": "03-08-2021", "confirmations": 20155, "deaths": 300, "recoveries": 19543}, {"id": "67", "day": "03-09-2021", "confirmations": 20155, "deaths": 300, "recoveries": 19543}, {"id": "68", "day": "03-10-2021", "confirmations": 20155, "deaths": 300, "recoveries": 19543}, {"id": "69", "day": "03-11-2021", "confirmations": 20155, "deaths": 300, "recoveries": 19543}, {"id": "70", "day": "03-12-2021", "confirmations": 20155, "deaths": 300, "recoveries": 19543}, {"id": "71", "day": "03-13-2021", "confirmations": 21356, "deaths": 326, "recoveries": 20380}, {"id": "72", "day": "03-14-2021", "confirmations": 21356, "deaths": 326, "recoveries": 20380}, {"id": "73", "day": "03-15-2021", "confirmations": 21587, "deaths": 334, "recoveries": 20494}, {"id": "74", "day": "03-16-2021", "confirmations": 21688, "deaths": 335, "recoveries": 20614}, {"id": "75", "day": "03-17-2021", "confirmations": 21826, "deaths": 337, "recoveries": 20670}, {"id": "76", "day": "03-18-2021", "confirmations": 21999, "deaths": 338, "recoveries": 20750}, {"id": "77", "day": "03-19-2021", "confirmations": 22113, "deaths": 340, "recoveries": 20851}, {"id": "78", "day": "03-20-2021", "confirmations": 22275, "deaths": 345, "recoveries": 20918}, {"id": "79", "day": "03-21-2021", "confirmations": 22484, "deaths": 351, "recoveries": 20996}, {"id": "80", "day": "03-22-2021", "confirmations": 22616, "deaths": 355, "recoveries": 21062}, {"id": "81", "day": "03-23-2021", "confirmations": 22682, "deaths": 361, "recoveries": 21141}, {"id": "82", "day": "03-24-2021", "confirmations": 22844, "deaths": 363, "recoveries": 21282}, {"id": "83", "day": "03-25-2021", "confirmations": 23040, "deaths": 369, "recoveries": 21372}, {"id": "84", "day": "03-26-2021", "confirmations": 23230, "deaths": 378, "recoveries": 21461}, {"id": "85", "day": "03-27-2021", "confirmations": 23424, "deaths": 381, "recoveries": 21569}, {"id": "86", "day": "03-28-2021", "confirmations": 23585, "deaths": 387, "recoveries": 21636}, {"id": "87", "day": "03-29-2021", "confirmations": 23969, "deaths": 394, "recoveries": 21671}, {"id": "88", "day": "03-30-2021", "confirmations": 24264, "deaths": 403, "recoveries": 21776}, {"id": "89", "day": "03-31-2021", "confirmations": 24426, "deaths": 418, "recoveries": 21908}, {"id": "90", "day": "04-01-2021", "confirmations": 24696, "deaths": 433, "recoveries": 22132}, {"id": "91", "day": "04-02-2021", "confirmations": 24968, "deaths": 444, "recoveries": 22300}, {"id": "92", "day": "04-03-2021", "confirmations": 25262, "deaths": 449, "recoveries": 22415}, {"id": "93", "day": "04-04-2021", "confirmations": 25572, "deaths": 454, "recoveries": 22559}, {"id": "94", "day": "04-05-2021", "confirmations": 25709, "deaths": 459, "recoveries": 22702}, {"id": "95", "day": "04-06-2021", "confirmations": 25874, "deaths": 462, "recoveries": 22813}, {"id": "96", "day": "04-07-2021", "confirmations": 26127, "deaths": 469, "recoveries": 22947}, {"id": "97", "day": "04-08-2021", "confirmations": 26475, "deaths": 475, "recoveries": 23092}, {"id": "98", "day": "04-09-2021", "confirmations": 27034, "deaths": 486, "recoveries": 23293}, {"id": "99", "day": "04-10-2021", "confirmations": 27548, "deaths": 493, "recoveries": 23481}, {"id": "100", "day": "04-11-2021", "confirmations": 28063, "deaths": 500, "recoveries": 23878}, {"id": "101", "day": "04-12-2021", "confirmations": 28541, "deaths": 506, "recoveries": 24105}, {"id": "102", "day": "04-13-2021", "confirmations": 28765, "deaths": 512, "recoveries": 24410}, {"id": "103", "day": "04-14-2021", "confirmations": 29348, "deaths": 520, "recoveries": 24695}, {"id": "104", "day": "04-15-2021", "confirmations": 30207, "deaths": 527, "recoveries": 24893}, {"id": "105", "day": "04-16-2021", "confirmations": 31039, "deaths": 531, "recoveries": 25193}, {"id": "106", "day": "04-17-2021", "confirmations": 31617, "deaths": 538, "recoveries": 25471}, {"id": "107", "day": "04-18-2021", "confirmations": 32205, "deaths": 542, "recoveries": 25798}, {"id": "108", "day": "04-19-2021", "confirmations": 32798, "deaths": 552, "recoveries": 26017}, {"id": "109", "day": "04-20-2021", "confirmations": 33202, "deaths": 563, "recoveries": 26291}, {"id": "110", "day": "04-21-2021", "confirmations": 33592, "deaths": 569, "recoveries": 26610}, {"id": "111", "day": "04-22-2021", "confirmations": 34069, "deaths": 579, "recoveries": 27152}, {"id": "112", "day": "04-23-2021", "confirmations": 34775, "deaths": 588, "recoveries": 27646}, {"id": "113", "day": "04-24-2021", "confirmations": 35262, "deaths": 593, "recoveries": 28132}, {"id": "114", "day": "04-25-2021", "confirmations": 35746, "deaths": 599, "recoveries": 28429}, {"id": "115", "day": "04-26-2021", "confirmations": 36045, "deaths": 605, "recoveries": 28868}, {"id": "116", "day": "04-27-2021", "confirmations": 36190, "deaths": 614, "recoveries": 29370}, {"id": "117", "day": "04-28-2021", "confirmations": 36510, "deaths": 631, "recoveries": 30070}, {"id": "118", "day": "04-29-2021", "confirmations": 36696, "deaths": 637, "recoveries": 31013}, {"id": "119", "day": "04-30-2021", "confirmations": 37014, "deaths": 643, "recoveries": 31570}, {"id": "120", "day": "05-01-2021", "confirmations": 37296, "deaths": 654, "recoveries": 32111}, {"id": "121", "day": "05-02-2021", "confirmations": 37630, "deaths": 666, "recoveries": 32747}, {"id": "122", "day": "05-03-2021", "confirmations": 37751, "deaths": 677, "recoveries": 33146}, {"id": "123", "day": "05-04-2021", "confirmations": 37989, "deaths": 682, "recoveries": 33568}, {"id": "124", "day": "05-05-2021", "confirmations": 38116, "deaths": 690, "recoveries": 34060}, {"id": "125", "day": "05-06-2021", "confirmations": 38337, "deaths": 695, "recoveries": 34727}, {"id": "126", "day": "05-07-2021", "confirmations": 38641, "deaths": 701, "recoveries": 35116}, {"id": "127", "day": "05-08-2021", "confirmations": 38874, "deaths": 716, "recoveries": 35732}, {"id": "128", "day": "05-09-2021", "confirmations": 39012, "deaths": 722, "recoveries": 36022}, {"id": "129", "day": "05-10-2021", "confirmations": 39162, "deaths": 729, "recoveries": 36255}, {"id": "130", "day": "05-11-2021", "confirmations": 39351, "deaths": 732, "recoveries": 36633}, {"id": "131", "day": "05-12-2021", "confirmations": 39510, "deaths": 738, "recoveries": 36881}, {"id": "132", "day": "05-13-2021", "confirmations": 39759, "deaths": 745, "recoveries": 37150}, {"id": "133", "day": "05-14-2021", "confirmations": 39888, "deaths": 748, "recoveries": 37431}, {"id": "134", "day": "05-15-2021", "confirmations": 40005, "deaths": 754, "recoveries": 37673}, {"id": "135", "day": "05-16-2021", "confirmations": 40141, "deaths": 763, "recoveries": 37823}, {"id": "136", "day": "05-17-2021", "confirmations": 40204, "deaths": 771, "recoveries": 37945}, {"id": "137", "day": "05-18-2021", "confirmations": 40326, "deaths": 774, "recoveries": 38166}, {"id": "138", "day": "05-19-2021", "confirmations": 40385, "deaths": 777, "recoveries": 38443}, {"id": "139", "day": "05-20-2021", "confirmations": 40519, "deaths": 783, "recoveries": 38679}, {"id": "140", "day": "05-21-2021", "confirmations": 40692, "deaths": 786, "recoveries": 38950}, {"id": "141", "day": "05-22-2021", "confirmations": 40780, "deaths": 793, "recoveries": 39101}, {"id": "142", "day": "05-23-2021", "confirmations": 40876, "deaths": 800, "recoveries": 39255}, {"id": "143", "day": "05-24-2021", "confirmations": 40954, "deaths": 806, "recoveries": 39410}, {"id": "144", "day": "05-25-2021", "confirmations": 40999, "deaths": 810, "recoveries": 39523}, {"id": "145", "day": "05-26-2021", "confirmations": 41061, "deaths": 817, "recoveries": 39763}, {"id": "146", "day": "05-27-2021", "confirmations": 41102, "deaths": 822, "recoveries": 39927}, {"id": "147", "day": "05-28-2021", "confirmations": 41184, "deaths": 827, "recoveries": 40028}, {"id": "148", "day": "05-29-2021", "confirmations": 41234, "deaths": 829, "recoveries": 40176}, {"id": "149", "day": "05-30-2021", "confirmations": 41266, "deaths": 835, "recoveries": 40281}, {"id": "150", "day": "05-31-2021", "confirmations": 41342, "deaths": 839, "recoveries": 40363}, {"id": "151", "day": "06-01-2021", "confirmations": 41366, "deaths": 841, "recoveries": 40485}, {"id": "152", "day": "06-02-2021", "confirmations": 41419, "deaths": 846, "recoveries": 40607}, {"id": "153", "day": "06-03-2021", "confirmations": 41488, "deaths": 850, "recoveries": 40774}, {"id": "154", "day": "06-04-2021", "confirmations": 41540, "deaths": 857, "recoveries": 40676}, {"id": "155", "day": "06-05-2021", "confirmations": 41631, "deaths": 859, "recoveries": 40758}, {"id": "156", "day": "06-06-2021", "confirmations": 41690, "deaths": 861, "recoveries": 40813}, {"id": "157", "day": "06-07-2021", "confirmations": 41742, "deaths": 866, "recoveries": 40870}, {"id": "158", "day": "06-08-2021", "confirmations": 41758, "deaths": 871, "recoveries": 40095}, {"id": "159", "day": "06-09-2021", "confirmations": 41786, "deaths": 874, "recoveries": 40130}, {"id": "160", "day": "06-10-2021", "confirmations": 41840, "deaths": 875, "recoveries": 40158}, {"id": "161", "day": "06-11-2021", "confirmations": 41869, "deaths": 879, "recoveries": 40190}, {"id": "162", "day": "06-12-2021", "confirmations": 41894, "deaths": 882, "recoveries": 40213}, {"id": "163", "day": "06-13-2021", "confirmations": 41933, "deaths": 887, "recoveries": 40239}, {"id": "164", "day": "06-14-2021", "confirmations": 41948, "deaths": 889, "recoveries": 40264}, {"id": "165", "day": "06-15-2021", "confirmations": 41966, "deaths": 891, "recoveries": 40279}, {"id": "166", "day": "06-16-2021", "confirmations": 41998, "deaths": 892, "recoveries": 40318}, {"id": "167", "day": "06-17-2021", "confirmations": 42034, "deaths": 892, "recoveries": 40345}, {"id": "168", "day": "06-18-2021", "confirmations": 42076, "deaths": 895, "recoveries": 40394}, {"id": "169", "day": "06-19-2021", "confirmations": 42087, "deaths": 896, "recoveries": 40425}, {"id": "170", "day": "06-20-2021", "confirmations": 42123, "deaths": 901, "recoveries": 40450}, {"id": "171", "day": "06-21-2021", "confirmations": 42137, "deaths": 903, "recoveries": 40469}, {"id": "172", "day": "06-22-2021", "confirmations": 42137, "deaths": 903, "recoveries": 40469}, {"id": "173", "day": "06-23-2021", "confirmations": 42161, "deaths": 905, "recoveries": 40500}, {"id": "174", "day": "06-24-2021", "confirmations": 42166, "deaths": 905, "recoveries": 40524}, {"id": "175", "day": "06-25-2021", "confirmations": 42194, "deaths": 906, "recoveries": 40569}, {"id": "176", "day": "06-26-2021", "confirmations": 42194, "deaths": 906, "recoveries": 40569}, {"id": "177", "day": "06-27-2021", "confirmations": 42194, "deaths": 906, "recoveries": 40569}, {"id": "178", "day": "06-28-2021", "confirmations": 42194, "deaths": 909, "recoveries": 40579}, {"id": "179", "day": "06-29-2021", "confirmations": 42207, "deaths": 911, "recoveries": 40610}, {"id": "180", "day": "06-30-2021", "confirmations": 42216, "deaths": 913, "recoveries": 40629}, {"id": "181", "day": "07-01-2021", "confirmations": 42247, "deaths": 915, "recoveries": 40651}, {"id": "182", "day": "07-02-2021", "confirmations": 42264, "deaths": 918, "recoveries": 40679}, {"id": "183", "day": "07-03-2021", "confirmations": 42288, "deaths": 921, "recoveries": 40709}, {"id": "184", "day": "07-04-2021", "confirmations": 42311, "deaths": 922, "recoveries": 40722}, {"id": "185", "day": "07-05-2021", "confirmations": 42329, "deaths": 924, "recoveries": 40736}, {"id": "186", "day": "07-06-2021", "confirmations": 42337, "deaths": 924, "recoveries": 40752}, {"id": "187", "day": "07-07-2021", "confirmations": 42358, "deaths": 926, "recoveries": 40767}, {"id": "188", "day": "07-08-2021", "confirmations": 42376, "deaths": 927, "recoveries": 40780}, {"id": "189", "day": "07-09-2021", "confirmations": 42392, "deaths": 928, "recoveries": 40798}, {"id": "190", "day": "07-10-2021", "confirmations": 42392, "deaths": 928, "recoveries": 40798}, {"id": "191", "day": "07-11-2021", "confirmations": 42392, "deaths": 928, "recoveries": 40798}, {"id": "192", "day": "07-12-2021", "confirmations": 42392, "deaths": 928, "recoveries": 40798}, {"id": "193", "day": "07-13-2021", "confirmations": 42462, "deaths": 933, "recoveries": 40845}, {"id": "194", "day": "07-14-2021", "confirmations": 42462, "deaths": 933, "recoveries": 40845}, {"id": "195", "day": "07-15-2021", "confirmations": 42479, "deaths": 934, "recoveries": 40862}, {"id": "196", "day": "07-16-2021", "confirmations": 42495, "deaths": 936, "recoveries": 40879}, {"id": "197", "day": "07-17-2021", "confirmations": 42520, "deaths": 936, "recoveries": 40891}, {"id": "198", "day": "07-18-2021", "confirmations": 42536, "deaths": 937, "recoveries": 40916}, {"id": "199", "day": "07-19-2021", "confirmations": 42538, "deaths": 937, "recoveries": 40932}, {"id": "200", "day": "07-20-2021", "confirmations": 42551, "deaths": 937, "recoveries": 40951}, {"id": "201", "day": "07-21-2021", "confirmations": 42558, "deaths": 937, "recoveries": 40972}, {"id": "202", "day": "07-22-2021", "confirmations": 42561, "deaths": 937, "recoveries": 40990}, {"id": "203", "day": "07-23-2021", "confirmations": 42581, "deaths": 939, "recoveries": 40999}, {"id": "204", "day": "07-24-2021", "confirmations": 42590, "deaths": 939, "recoveries": 41014}, {"id": "205", "day": "07-25-2021", "confirmations": 42599, "deaths": 939, "recoveries": 41027}, {"id": "206", "day": "07-26-2021", "confirmations": 42599, "deaths": 940, "recoveries": 41039}, {"id": "207", "day": "07-27-2021", "confirmations": 42607, "deaths": 941, "recoveries": 41066}, {"id": "208", "day": "07-28-2021", "confirmations": 42615, "deaths": 942, "recoveries": 41091}, {"id": "209", "day": "07-29-2021", "confirmations": 42645, "deaths": 942, "recoveries": 41109}, {"id": "210", "day": "07-30-2021", "confirmations": 42652, "deaths": 943, "recoveries": 41127}, {"id": "211", "day": "07-31-2021", "confirmations": 42663, "deaths": 943, "recoveries": 41143}, {"id": "212", "day": "08-01-2021", "confirmations": 42665, "deaths": 943, "recoveries": 41151}, {"id": "213", "day": "08-02-2021", "confirmations": 42672, "deaths": 943, "recoveries": 41164}, {"id": "214", "day": "08-03-2021", "confirmations": 42674, "deaths": 943, "recoveries": 41173}, {"id": "215", "day": "08-04-2021", "confirmations": 42685, "deaths": 943, "recoveries": 41177}, {"id": "216", "day": "08-05-2021", "confirmations": 42685, "deaths": 943, "recoveries": 0}, {"id": "217", "day": "08-06-2021", "confirmations": 42685, "deaths": 943, "recoveries": 0}, {"id": "218", "day": "08-07-2021", "confirmations": 42685, "deaths": 943, "recoveries": 0}, {"id": "219", "day": "08-08-2021", "confirmations": 42776, "deaths": 948, "recoveries": 0}, {"id": "220", "day": "08-09-2021", "confirmations": 42781, "deaths": 948, "recoveries": 0}, {"id": "221", "day": "08-10-2021", "confirmations": 42787, "deaths": 948, "recoveries": 0}, {"id": "222", "day": "08-11-2021", "confirmations": 42791, "deaths": 949, "recoveries": 0}, {"id": "223", "day": "08-12-2021", "confirmations": 42795, "deaths": 950, "recoveries": 0}, {"id": "224", "day": "08-13-2021", "confirmations": 42802, "deaths": 951, "recoveries": 0}, {"id": "225", "day": "08-14-2021", "confirmations": 42811, "deaths": 952, "recoveries": 0}, {"id": "226", "day": "08-15-2021", "confirmations": 42811, "deaths": 952, "recoveries": 0}, {"id": "227", "day": "08-16-2021", "confirmations": 42819, "deaths": 954, "recoveries": 0}, {"id": "228", "day": "08-17-2021", "confirmations": 42819, "deaths": 954, "recoveries": 0}, {"id": "229", "day": "08-18-2021", "confirmations": 42832, "deaths": 954, "recoveries": 0}, {"id": "230", "day": "08-19-2021", "confirmations": 42836, "deaths": 954, "recoveries": 0}, {"id": "231", "day": "08-20-2021", "confirmations": 42838, "deaths": 954, "recoveries": 0}, {"id": "232", "day": "08-21-2021", "confirmations": 42842, "deaths": 954, "recoveries": 0}, {"id": "233", "day": "08-22-2021", "confirmations": 42845, "deaths": 954, "recoveries": 0}, {"id": "234", "day": "08-23-2021", "confirmations": 42847, "deaths": 955, "recoveries": 0}, {"id": "235", "day": "08-24-2021", "confirmations": 42847, "deaths": 955, "recoveries": 0}, {"id": "236", "day": "08-25-2021", "confirmations": 42850, "deaths": 955, "recoveries": 0}, {"id": "237", "day": "08-26-2021", "confirmations": 42854, "deaths": 955, "recoveries": 0}, {"id": "238", "day": "08-27-2021", "confirmations": 42857, "deaths": 955, "recoveries": 0}, {"id": "239", "day": "08-28-2021", "confirmations": 42862, "deaths": 955, "recoveries": 0}, {"id": "240", "day": "08-29-2021", "confirmations": 42862, "deaths": 955, "recoveries": 0}, {"id": "241", "day": "08-30-2021", "confirmations": 42862, "deaths": 955, "recoveries": 0}, {"id": "242", "day": "08-31-2021", "confirmations": 42869, "deaths": 956, "recoveries": 0}, {"id": "243", "day": "09-01-2021", "confirmations": 42873, "deaths": 956, "recoveries": 0}, {"id": "244", "day": "09-02-2021", "confirmations": 42873, "deaths": 956, "recoveries": 0}, {"id": "245", "day": "09-03-2021", "confirmations": 42878, "deaths": 956, "recoveries": 0}, {"id": "246", "day": "09-04-2021", "confirmations": 42881, "deaths": 957, "recoveries": 0}, {"id": "247", "day": "09-05-2021", "confirmations": 42884, "deaths": 957, "recoveries": 0}, {"id": "248", "day": "09-06-2021", "confirmations": 42884, "deaths": 957, "recoveries": 0}, {"id": "249", "day": "09-07-2021", "confirmations": 42884, "deaths": 957, "recoveries": 0}, {"id": "250", "day": "09-08-2021", "confirmations": 42884, "deaths": 957, "recoveries": 0}, {"id": "251", "day": "09-09-2021", "confirmations": 42884, "deaths": 957, "recoveries": 0}, {"id": "252", "day": "09-10-2021", "confirmations": 42891, "deaths": 958, "recoveries": 0}, {"id": "253", "day": "09-11-2021", "confirmations": 42894, "deaths": 958, "recoveries": 0}, {"id": "254", "day": "09-12-2021", "confirmations": 42894, "deaths": 958, "recoveries": 0}, {"id": "255", "day": "09-13-2021", "confirmations": 42898, "deaths": 958, "recoveries": 0}, {"id": "256", "day": "09-14-2021", "confirmations": 42898, "deaths": 958, "recoveries": 0}, {"id": "257", "day": "09-15-2021", "confirmations": 42898, "deaths": 958, "recoveries": 0}, {"id": "258", "day": "09-16-2021", "confirmations": 42898, "deaths": 958, "recoveries": 0}, {"id": "259", "day": "09-17-2021", "confirmations": 42898, "deaths": 958, "recoveries": 0}, {"id": "260", "day": "09-18-2021", "confirmations": 42898, "deaths": 958, "recoveries": 0}, {"id": "261", "day": "09-19-2021", "confirmations": 42898, "deaths": 958, "recoveries": 0}, {"id": "262", "day": "09-20-2021", "confirmations": 42898, "deaths": 958, "recoveries": 0}, {"id": "263", "day": "09-21-2021", "confirmations": 42898, "deaths": 958, "recoveries": 0}, {"id": "264", "day": "09-22-2021", "confirmations": 42898, "deaths": 958, "recoveries": 0}, {"id": "265", "day": "09-23-2021", "confirmations": 42898, "deaths": 958, "recoveries": 0}, {"id": "266", "day": "09-24-2021", "confirmations": 42898, "deaths": 958, "recoveries": 0}, {"id": "267", "day": "09-25-2021", "confirmations": 42898, "deaths": 958, "recoveries": 0}, {"id": "268", "day": "09-26-2021", "confirmations": 42898, "deaths": 958, "recoveries": 0}, {"id": "269", "day": "09-27-2021", "confirmations": 42898, "deaths": 958, "recoveries": 0}, {"id": "270", "day": "09-28-2021", "confirmations": 42898, "deaths": 958, "recoveries": 0}, {"id": "271", "day": "09-29-2021", "confirmations": 42898, "deaths": 958, "recoveries": 0}, {"id": "272", "day": "09-30-2021", "confirmations": 42898, "deaths": 958, "recoveries": 0}, {"id": "273", "day": "10-01-2021", "confirmations": 42898, "deaths": 958, "recoveries": 0}, {"id": "274", "day": "10-02-2021", "confirmations": 42898, "deaths": 958, "recoveries": 0}, {"id": "275", "day": "10-03-2021", "confirmations": 42898, "deaths": 958, "recoveries": 0}, {"id": "276", "day": "10-04-2021", "confirmations": 42898, "deaths": 958, "recoveries": 0}, {"id": "277", "day": "10-05-2021", "confirmations": 42898, "deaths": 958, "recoveries": 0}, {"id": "278", "day": "10-06-2021", "confirmations": 43610, "deaths": 960, "recoveries": 0}, {"id": "279", "day": "10-07-2021", "confirmations": 43610, "deaths": 960, "recoveries": 0}, {"id": "280", "day": "10-08-2021", "confirmations": 43610, "deaths": 960, "recoveries": 0}, {"id": "281", "day": "10-09-2021", "confirmations": 43610, "deaths": 960, "recoveries": 0}, {"id": "282", "day": "10-10-2021", "confirmations": 43610, "deaths": 960, "recoveries": 0}, {"id": "283", "day": "10-11-2021", "confirmations": 43610, "deaths": 960, "recoveries": 0}, {"id": "284", "day": "10-12-2021", "confirmations": 43610, "deaths": 960, "recoveries": 0}, {"id": "285", "day": "10-13-2021", "confirmations": 43610, "deaths": 960, "recoveries": 0}, {"id": "286", "day": "10-14-2021", "confirmations": 43616, "deaths": 960, "recoveries": 0}, {"id": "287", "day": "10-15-2021", "confirmations": 43616, "deaths": 960, "recoveries": 0}, {"id": "288", "day": "10-16-2021", "confirmations": 43616, "deaths": 960, "recoveries": 0}, {"id": "289", "day": "10-17-2021", "confirmations": 43616, "deaths": 960, "recoveries": 0}, {"id": "290", "day": "10-18-2021", "confirmations": 43616, "deaths": 960, "recoveries": 0}, {"id": "291", "day": "10-19-2021", "confirmations": 43622, "deaths": 960, "recoveries": 0}, {"id": "292", "day": "10-20-2021", "confirmations": 43622, "deaths": 960, "recoveries": 0}, {"id": "293", "day": "10-21-2021", "confirmations": 43622, "deaths": 960, "recoveries": 0}, {"id": "294", "day": "10-22-2021", "confirmations": 43622, "deaths": 960, "recoveries": 0}, {"id": "295", "day": "10-23-2021", "confirmations": 43622, "deaths": 960, "recoveries": 0}, {"id": "296", "day": "10-24-2021", "confirmations": 43622, "deaths": 960, "recoveries": 0}, {"id": "297", "day": "10-25-2021", "confirmations": 43622, "deaths": 960, "recoveries": 0}, {"id": "298", "day": "10-26-2021", "confirmations": 43626, "deaths": 963, "recoveries": 0}, {"id": "299", "day": "10-27-2021", "confirmations": 43626, "deaths": 963, "recoveries": 0}, {"id": "300", "day": "10-28-2021", "confirmations": 43626, "deaths": 963, "recoveries": 0}, {"id": "301", "day": "10-29-2021", "confirmations": 43626, "deaths": 963, "recoveries": 0}, {"id": "302", "day": "10-30-2021", "confirmations": 43626, "deaths": 963, "recoveries": 0}, {"id": "303", "day": "10-31-2021", "confirmations": 43626, "deaths": 963, "recoveries": 0}, {"id": "304", "day": "11-01-2021", "confirmations": 43626, "deaths": 963, "recoveries": 0}, {"id": "305", "day": "11-02-2021", "confirmations": 43632, "deaths": 964, "recoveries": 0}, {"id": "306", "day": "11-03-2021", "confirmations": 43632, "deaths": 964, "recoveries": 0}, {"id": "307", "day": "11-04-2021", "confirmations": 43632, "deaths": 964, "recoveries": 0}, {"id": "308", "day": "11-05-2021", "confirmations": 43632, "deaths": 964, "recoveries": 0}, {"id": "309", "day": "11-06-2021", "confirmations": 43632, "deaths": 964, "recoveries": 0}, {"id": "310", "day": "11-07-2021", "confirmations": 43632, "deaths": 964, "recoveries": 0}, {"id": "311", "day": "11-08-2021", "confirmations": 43632, "deaths": 964, "recoveries": 0}, {"id": "312", "day": "11-09-2021", "confirmations": 43632, "deaths": 964, "recoveries": 0}, {"id": "313", "day": "11-10-2021", "confirmations": 43672, "deaths": 964, "recoveries": 0}, {"id": "314", "day": "11-11-2021", "confirmations": 43672, "deaths": 964, "recoveries": 0}, {"id": "315", "day": "11-12-2021", "confirmations": 43672, "deaths": 964, "recoveries": 0}, {"id": "316", "day": "11-13-2021", "confirmations": 43672, "deaths": 964, "recoveries": 0}, {"id": "317", "day": "11-14-2021", "confirmations": 43672, "deaths": 964, "recoveries": 0}, {"id": "318", "day": "11-15-2021", "confirmations": 43672, "deaths": 964, "recoveries": 0}, {"id": "319", "day": "11-16-2021", "confirmations": 43672, "deaths": 964, "recoveries": 0}, {"id": "320", "day": "11-17-2021", "confirmations": 43672, "deaths": 964, "recoveries": 0}, {"id": "321", "day": "11-18-2021", "confirmations": 43672, "deaths": 964, "recoveries": 0}, {"id": "322", "day": "11-19-2021", "confirmations": 43672, "deaths": 964, "recoveries": 0}, {"id": "323", "day": "11-20-2021", "confirmations": 43672, "deaths": 964, "recoveries": 0}, {"id": "324", "day": "11-21-2021", "confirmations": 43672, "deaths": 964, "recoveries": 0}, {"id": "325", "day": "11-22-2021", "confirmations": 43672, "deaths": 964, "recoveries": 0}, {"id": "326", "day": "11-23-2021", "confirmations": 44072, "deaths": 967, "recoveries": 0}, {"id": "327", "day": "11-24-2021", "confirmations": 44072, "deaths": 967, "recoveries": 0}, {"id": "328", "day": "11-25-2021", "confirmations": 44072, "deaths": 967, "recoveries": 0}, {"id": "329", "day": "11-26-2021", "confirmations": 44072, "deaths": 967, "recoveries": 0}, {"id": "330", "day": "11-27-2021", "confirmations": 44072, "deaths": 967, "recoveries": 0}, {"id": "331", "day": "11-28-2021", "confirmations": 44072, "deaths": 967, "recoveries": 0}, {"id": "332", "day": "11-29-2021", "confirmations": 44330, "deaths": 967, "recoveries": 0}, {"id": "333", "day": "11-30-2021", "confirmations": 44330, "deaths": 967, "recoveries": 0}, {"id": "334", "day": "12-01-2021", "confirmations": 44330, "deaths": 967, "recoveries": 0}, {"id": "335", "day": "12-02-2021", "confirmations": 44330, "deaths": 967, "recoveries": 0}, {"id": "336", "day": "12-03-2021", "confirmations": 44330, "deaths": 967, "recoveries": 0}, {"id": "337", "day": "12-04-2021", "confirmations": 44800, "deaths": 972, "recoveries": 0}, {"id": "338", "day": "12-05-2021", "confirmations": 44800, "deaths": 972, "recoveries": 0}, {"id": "339", "day": "12-06-2021", "confirmations": 44800, "deaths": 972, "recoveries": 0}, {"id": "340", "day": "12-07-2021", "confirmations": 44800, "deaths": 972, "recoveries": 0}, {"id": "341", "day": "12-08-2021", "confirmations": 44800, "deaths": 972, "recoveries": 0}, {"id": "342", "day": "12-09-2021", "confirmations": 44800, "deaths": 972, "recoveries": 0}, {"id": "343", "day": "12-10-2021", "confirmations": 44800, "deaths": 972, "recoveries": 0}, {"id": "344", "day": "12-11-2021", "confirmations": 45794, "deaths": 980, "recoveries": 0}, {"id": "345", "day": "12-12-2021", "confirmations": 45794, "deaths": 980, "recoveries": 0}, {"id": "346", "day": "12-13-2021", "confirmations": 45794, "deaths": 980, "recoveries": 0}, {"id": "347", "day": "12-14-2021", "confirmations": 45794, "deaths": 980, "recoveries": 0}, {"id": "348", "day": "12-15-2021", "confirmations": 45794, "deaths": 980, "recoveries": 0}, {"id": "349", "day": "12-16-2021", "confirmations": 45794, "deaths": 980, "recoveries": 0}, {"id": "350", "day": "12-17-2021", "confirmations": 45794, "deaths": 980, "recoveries": 0}, {"id": "351", "day": "12-18-2021", "confirmations": 47295, "deaths": 996, "recoveries": 0}, {"id": "352", "day": "12-19-2021", "confirmations": 47295, "deaths": 996, "recoveries": 0}, {"id": "353", "day": "12-20-2021", "confirmations": 47295, "deaths": 996, "recoveries": 0}, {"id": "354", "day": "12-21-2021", "confirmations": 47295, "deaths": 996, "recoveries": 0}, {"id": "355", "day": "12-22-2021", "confirmations": 47295, "deaths": 996, "recoveries": 0}, {"id": "356", "day": "12-23-2021", "confirmations": 47295, "deaths": 996, "recoveries": 0}, {"id": "357", "day": "12-24-2021", "confirmations": 47295, "deaths": 996, "recoveries": 0}, {"id": "358", "day": "12-25-2021", "confirmations": 49590, "deaths": 1027, "recoveries": 0}, {"id": "359", "day": "12-26-2021", "confirmations": 49590, "deaths": 1027, "recoveries": 0}, {"id": "360", "day": "12-27-2021", "confirmations": 49590, "deaths": 1027, "recoveries": 0}, {"id": "361", "day": "12-28-2021", "confirmations": 49590, "deaths": 1027, "recoveries": 0}, {"id": "362", "day": "12-29-2021", "confirmations": 50279, "deaths": 1027, "recoveries": 0}, {"id": "363", "day": "12-30-2021", "confirmations": 50279, "deaths": 1027, "recoveries": 0}, {"id": "364", "day": "12-31-2021", "confirmations": 50279, "deaths": 1027, "recoveries": 0}, {"id": "365", "day": "01-01-2022", "confirmations": 50279, "deaths": 1027, "recoveries": 0}, {"id": "366", "day": "01-02-2022", "confirmations": 50279, "deaths": 1027, "recoveries": 0}, {"id": "367", "day": "01-03-2022", "confirmations": 50279, "deaths": 1027, "recoveries": 0}, {"id": "368", "day": "01-04-2022", "confirmations": 52434, "deaths": 1067, "recoveries": 0}, {"id": "369", "day": "01-05-2022", "confirmations": 52434, "deaths": 1067, "recoveries": 0}, {"id": "370", "day": "01-06-2022", "confirmations": 52434, "deaths": 1067, "recoveries": 0}, {"id": "371", "day": "01-07-2022", "confirmations": 52434, "deaths": 1067, "recoveries": 0}, {"id": "372", "day": "01-08-2022", "confirmations": 54101, "deaths": 1117, "recoveries": 0}, {"id": "373", "day": "01-09-2022", "confirmations": 54101, "deaths": 1117, "recoveries": 0}]}