{"id": "3967", "key": "Wales, United Kingdom", "data": [{"id": "0", "day": "01-01-2021", "confirmations": 148537, "deaths": 3494, "recoveries": 0}, {"id": "1", "day": "01-02-2021", "confirmations": 151300, "deaths": 3564, "recoveries": 0}, {"id": "2", "day": "01-03-2021", "confirmations": 155311, "deaths": 3620, "recoveries": 0}, {"id": "3", "day": "01-04-2021", "confirmations": 157209, "deaths": 3645, "recoveries": 0}, {"id": "4", "day": "01-05-2021", "confirmations": 159278, "deaths": 3662, "recoveries": 0}, {"id": "5", "day": "01-06-2021", "confirmations": 161516, "deaths": 3738, "recoveries": 0}, {"id": "6", "day": "01-07-2021", "confirmations": 163234, "deaths": 3801, "recoveries": 0}, {"id": "7", "day": "01-08-2021", "confirmations": 165721, "deaths": 3857, "recoveries": 0}, {"id": "8", "day": "01-09-2021", "confirmations": 168094, "deaths": 3919, "recoveries": 0}, {"id": "9", "day": "01-10-2021", "confirmations": 169754, "deaths": 3964, "recoveries": 0}, {"id": "10", "day": "01-11-2021", "confirmations": 171547, "deaths": 3981, "recoveries": 0}, {"id": "11", "day": "01-12-2021", "confirmations": 172879, "deaths": 3997, "recoveries": 0}, {"id": "12", "day": "01-13-2021", "confirmations": 174412, "deaths": 4063, "recoveries": 0}, {"id": "13", "day": "01-14-2021", "confirmations": 176056, "deaths": 4117, "recoveries": 0}, {"id": "14", "day": "01-15-2021", "confirmations": 177864, "deaths": 4171, "recoveries": 0}, {"id": "15", "day": "01-16-2021", "confirmations": 178989, "deaths": 4226, "recoveries": 0}, {"id": "16", "day": "01-17-2021", "confirmations": 180161, "deaths": 4274, "recoveries": 0}, {"id": "17", "day": "01-18-2021", "confirmations": 181493, "deaths": 4294, "recoveries": 0}, {"id": "18", "day": "01-19-2021", "confirmations": 182599, "deaths": 4302, "recoveries": 0}, {"id": "19", "day": "01-20-2021", "confirmations": 183882, "deaths": 4346, "recoveries": 0}, {"id": "20", "day": "01-21-2021", "confirmations": 185035, "deaths": 4392, "recoveries": 0}, {"id": "21", "day": "01-22-2021", "confirmations": 185836, "deaths": 4459, "recoveries": 0}, {"id": "22", "day": "01-23-2021", "confirmations": 186915, "deaths": 4486, "recoveries": 0}, {"id": "23", "day": "01-24-2021", "confirmations": 187711, "deaths": 4530, "recoveries": 0}, {"id": "24", "day": "01-25-2021", "confirmations": 188583, "deaths": 4553, "recoveries": 0}, {"id": "25", "day": "01-26-2021", "confirmations": 189152, "deaths": 4561, "recoveries": 0}, {"id": "26", "day": "01-27-2021", "confirmations": 189689, "deaths": 4610, "recoveries": 0}, {"id": "27", "day": "01-28-2021", "confirmations": 190394, "deaths": 4666, "recoveries": 0}, {"id": "28", "day": "01-29-2021", "confirmations": 190940, "deaths": 4695, "recoveries": 0}, {"id": "29", "day": "01-30-2021", "confirmations": 191677, "deaths": 4720, "recoveries": 0}, {"id": "30", "day": "01-31-2021", "confirmations": 192282, "deaths": 4754, "recoveries": 0}, {"id": "31", "day": "02-01-2021", "confirmations": 192912, "deaths": 4775, "recoveries": 0}, {"id": "32", "day": "02-02-2021", "confirmations": 193526, "deaths": 4782, "recoveries": 0}, {"id": "33", "day": "02-03-2021", "confirmations": 193981, "deaths": 4832, "recoveries": 0}, {"id": "34", "day": "02-04-2021", "confirmations": 194525, "deaths": 4867, "recoveries": 0}, {"id": "35", "day": "02-05-2021", "confirmations": 194924, "deaths": 4912, "recoveries": 0}, {"id": "36", "day": "02-06-2021", "confirmations": 195599, "deaths": 4961, "recoveries": 0}, {"id": "37", "day": "02-07-2021", "confirmations": 196060, "deaths": 4989, "recoveries": 0}, {"id": "38", "day": "02-08-2021", "confirmations": 196670, "deaths": 5001, "recoveries": 0}, {"id": "39", "day": "02-09-2021", "confirmations": 197021, "deaths": 5011, "recoveries": 0}, {"id": "40", "day": "02-10-2021", "confirmations": 197344, "deaths": 5032, "recoveries": 0}, {"id": "41", "day": "02-11-2021", "confirmations": 197754, "deaths": 5059, "recoveries": 0}, {"id": "42", "day": "02-12-2021", "confirmations": 198362, "deaths": 5084, "recoveries": 0}, {"id": "43", "day": "02-13-2021", "confirmations": 198761, "deaths": 5106, "recoveries": 0}, {"id": "44", "day": "02-14-2021", "confirmations": 199155, "deaths": 5121, "recoveries": 0}, {"id": "45", "day": "02-15-2021", "confirmations": 199518, "deaths": 5137, "recoveries": 0}, {"id": "46", "day": "02-16-2021", "confirmations": 199793, "deaths": 5145, "recoveries": 0}, {"id": "47", "day": "02-17-2021", "confirmations": 200166, "deaths": 5175, "recoveries": 0}, {"id": "48", "day": "02-18-2021", "confirmations": 200456, "deaths": 5189, "recoveries": 0}, {"id": "49", "day": "02-19-2021", "confirmations": 200989, "deaths": 5205, "recoveries": 0}, {"id": "50", "day": "02-20-2021", "confirmations": 201352, "deaths": 5221, "recoveries": 0}, {"id": "51", "day": "02-21-2021", "confirmations": 201688, "deaths": 5237, "recoveries": 0}, {"id": "52", "day": "02-22-2021", "confirmations": 202007, "deaths": 5246, "recoveries": 0}, {"id": "53", "day": "02-23-2021", "confirmations": 202324, "deaths": 5250, "recoveries": 0}, {"id": "54", "day": "02-24-2021", "confirmations": 202560, "deaths": 5263, "recoveries": 0}, {"id": "55", "day": "02-25-2021", "confirmations": 202872, "deaths": 5284, "recoveries": 0}, {"id": "56", "day": "02-26-2021", "confirmations": 203180, "deaths": 5300, "recoveries": 0}, {"id": "57", "day": "02-27-2021", "confirmations": 203378, "deaths": 5316, "recoveries": 0}, {"id": "58", "day": "02-28-2021", "confirmations": 203625, "deaths": 5340, "recoveries": 0}, {"id": "59", "day": "03-01-2021", "confirmations": 203818, "deaths": 5343, "recoveries": 0}, {"id": "60", "day": "03-02-2021", "confirmations": 203988, "deaths": 5344, "recoveries": 0}, {"id": "61", "day": "03-03-2021", "confirmations": 204196, "deaths": 5356, "recoveries": 0}, {"id": "62", "day": "03-04-2021", "confirmations": 204463, "deaths": 5366, "recoveries": 0}, {"id": "63", "day": "03-05-2021", "confirmations": 204692, "deaths": 5378, "recoveries": 0}, {"id": "64", "day": "03-06-2021", "confirmations": 204886, "deaths": 5385, "recoveries": 0}, {"id": "65", "day": "03-07-2021", "confirmations": 205038, "deaths": 5403, "recoveries": 0}, {"id": "66", "day": "03-08-2021", "confirmations": 205202, "deaths": 5403, "recoveries": 0}, {"id": "67", "day": "03-09-2021", "confirmations": 205368, "deaths": 5406, "recoveries": 0}, {"id": "68", "day": "03-10-2021", "confirmations": 205593, "deaths": 5412, "recoveries": 0}, {"id": "69", "day": "03-11-2021", "confirmations": 205788, "deaths": 5424, "recoveries": 0}, {"id": "70", "day": "03-12-2021", "confirmations": 205978, "deaths": 5436, "recoveries": 0}, {"id": "71", "day": "03-13-2021", "confirmations": 206188, "deaths": 5442, "recoveries": 0}, {"id": "72", "day": "03-14-2021", "confirmations": 206405, "deaths": 5452, "recoveries": 0}, {"id": "73", "day": "03-15-2021", "confirmations": 206653, "deaths": 5454, "recoveries": 0}, {"id": "74", "day": "03-16-2021", "confirmations": 206795, "deaths": 5455, "recoveries": 0}, {"id": "75", "day": "03-17-2021", "confirmations": 206940, "deaths": 5463, "recoveries": 0}, {"id": "76", "day": "03-18-2021", "confirmations": 207237, "deaths": 5467, "recoveries": 0}, {"id": "77", "day": "03-19-2021", "confirmations": 207438, "deaths": 5476, "recoveries": 0}, {"id": "78", "day": "03-20-2021", "confirmations": 207646, "deaths": 5482, "recoveries": 0}, {"id": "79", "day": "03-21-2021", "confirmations": 207842, "deaths": 5488, "recoveries": 0}, {"id": "80", "day": "03-22-2021", "confirmations": 207992, "deaths": 5488, "recoveries": 0}, {"id": "81", "day": "03-23-2021", "confirmations": 208119, "deaths": 5488, "recoveries": 0}, {"id": "82", "day": "03-24-2021", "confirmations": 208277, "deaths": 5491, "recoveries": 0}, {"id": "83", "day": "03-25-2021", "confirmations": 208504, "deaths": 5495, "recoveries": 0}, {"id": "84", "day": "03-26-2021", "confirmations": 208694, "deaths": 5498, "recoveries": 0}, {"id": "85", "day": "03-27-2021", "confirmations": 208895, "deaths": 5505, "recoveries": 0}, {"id": "86", "day": "03-28-2021", "confirmations": 209066, "deaths": 5505, "recoveries": 0}, {"id": "87", "day": "03-29-2021", "confirmations": 209191, "deaths": 5506, "recoveries": 0}, {"id": "88", "day": "03-30-2021", "confirmations": 209285, "deaths": 5506, "recoveries": 0}, {"id": "89", "day": "03-31-2021", "confirmations": 209345, "deaths": 5507, "recoveries": 0}, {"id": "90", "day": "04-01-2021", "confirmations": 209532, "deaths": 5509, "recoveries": 0}, {"id": "91", "day": "04-02-2021", "confirmations": 209532, "deaths": 5509, "recoveries": 0}, {"id": "92", "day": "04-03-2021", "confirmations": 209627, "deaths": 5511, "recoveries": 0}, {"id": "93", "day": "04-04-2021", "confirmations": 209627, "deaths": 5511, "recoveries": 0}, {"id": "94", "day": "04-05-2021", "confirmations": 209816, "deaths": 5519, "recoveries": 0}, {"id": "95", "day": "04-06-2021", "confirmations": 209942, "deaths": 5521, "recoveries": 0}, {"id": "96", "day": "04-07-2021", "confirmations": 210023, "deaths": 5521, "recoveries": 0}, {"id": "97", "day": "04-08-2021", "confirmations": 210105, "deaths": 5527, "recoveries": 0}, {"id": "98", "day": "04-09-2021", "confirmations": 210219, "deaths": 5528, "recoveries": 0}, {"id": "99", "day": "04-10-2021", "confirmations": 210344, "deaths": 5528, "recoveries": 0}, {"id": "100", "day": "04-11-2021", "confirmations": 210397, "deaths": 5531, "recoveries": 0}, {"id": "101", "day": "04-12-2021", "confirmations": 210447, "deaths": 5531, "recoveries": 0}, {"id": "102", "day": "04-13-2021", "confirmations": 210515, "deaths": 5533, "recoveries": 0}, {"id": "103", "day": "04-14-2021", "confirmations": 210577, "deaths": 5533, "recoveries": 0}, {"id": "104", "day": "04-15-2021", "confirmations": 210681, "deaths": 5535, "recoveries": 0}, {"id": "105", "day": "04-16-2021", "confirmations": 210729, "deaths": 5535, "recoveries": 0}, {"id": "106", "day": "04-17-2021", "confirmations": 210729, "deaths": 5535, "recoveries": 0}, {"id": "107", "day": "04-18-2021", "confirmations": 210823, "deaths": 5538, "recoveries": 0}, {"id": "108", "day": "04-19-2021", "confirmations": 210925, "deaths": 5540, "recoveries": 0}, {"id": "109", "day": "04-20-2021", "confirmations": 210978, "deaths": 5542, "recoveries": 0}, {"id": "110", "day": "04-21-2021", "confirmations": 211042, "deaths": 5542, "recoveries": 0}, {"id": "111", "day": "04-22-2021", "confirmations": 211104, "deaths": 5543, "recoveries": 0}, {"id": "112", "day": "04-23-2021", "confirmations": 211162, "deaths": 5543, "recoveries": 0}, {"id": "113", "day": "04-24-2021", "confirmations": 211162, "deaths": 5543, "recoveries": 0}, {"id": "114", "day": "04-25-2021", "confirmations": 211224, "deaths": 5546, "recoveries": 0}, {"id": "115", "day": "04-26-2021", "confirmations": 211321, "deaths": 5548, "recoveries": 0}, {"id": "116", "day": "04-27-2021", "confirmations": 211354, "deaths": 5548, "recoveries": 0}, {"id": "117", "day": "04-28-2021", "confirmations": 211389, "deaths": 5548, "recoveries": 0}, {"id": "118", "day": "04-29-2021", "confirmations": 211458, "deaths": 5550, "recoveries": 0}, {"id": "119", "day": "04-30-2021", "confirmations": 211494, "deaths": 5550, "recoveries": 0}, {"id": "120", "day": "05-01-2021", "confirmations": 211494, "deaths": 5550, "recoveries": 0}, {"id": "121", "day": "05-02-2021", "confirmations": 211573, "deaths": 5550, "recoveries": 0}, {"id": "122", "day": "05-03-2021", "confirmations": 211573, "deaths": 5550, "recoveries": 0}, {"id": "123", "day": "05-04-2021", "confirmations": 211638, "deaths": 5551, "recoveries": 0}, {"id": "124", "day": "05-05-2021", "confirmations": 211692, "deaths": 5551, "recoveries": 0}, {"id": "125", "day": "05-06-2021", "confirmations": 211726, "deaths": 5552, "recoveries": 0}, {"id": "126", "day": "05-07-2021", "confirmations": 211773, "deaths": 5552, "recoveries": 0}, {"id": "127", "day": "05-08-2021", "confirmations": 211773, "deaths": 5552, "recoveries": 0}, {"id": "128", "day": "05-09-2021", "confirmations": 211827, "deaths": 5552, "recoveries": 0}, {"id": "129", "day": "05-10-2021", "confirmations": 211931, "deaths": 5556, "recoveries": 0}, {"id": "130", "day": "05-11-2021", "confirmations": 211961, "deaths": 5557, "recoveries": 0}, {"id": "131", "day": "05-12-2021", "confirmations": 211983, "deaths": 5557, "recoveries": 0}, {"id": "132", "day": "05-13-2021", "confirmations": 212041, "deaths": 5558, "recoveries": 0}, {"id": "133", "day": "05-14-2021", "confirmations": 212095, "deaths": 5558, "recoveries": 0}, {"id": "134", "day": "05-15-2021", "confirmations": 212095, "deaths": 5558, "recoveries": 0}, {"id": "135", "day": "05-16-2021", "confirmations": 212149, "deaths": 5559, "recoveries": 0}, {"id": "136", "day": "05-17-2021", "confirmations": 212240, "deaths": 5560, "recoveries": 0}, {"id": "137", "day": "05-18-2021", "confirmations": 212272, "deaths": 5560, "recoveries": 0}, {"id": "138", "day": "05-19-2021", "confirmations": 212316, "deaths": 5560, "recoveries": 0}, {"id": "139", "day": "05-20-2021", "confirmations": 212361, "deaths": 5561, "recoveries": 0}, {"id": "140", "day": "05-21-2021", "confirmations": 212388, "deaths": 5564, "recoveries": 0}, {"id": "141", "day": "05-22-2021", "confirmations": 212388, "deaths": 5564, "recoveries": 0}, {"id": "142", "day": "05-23-2021", "confirmations": 212434, "deaths": 5566, "recoveries": 0}, {"id": "143", "day": "05-24-2021", "confirmations": 212535, "deaths": 5566, "recoveries": 0}, {"id": "144", "day": "05-25-2021", "confirmations": 212554, "deaths": 5566, "recoveries": 0}, {"id": "145", "day": "05-26-2021", "confirmations": 212582, "deaths": 5567, "recoveries": 0}, {"id": "146", "day": "05-27-2021", "confirmations": 212640, "deaths": 5569, "recoveries": 0}, {"id": "147", "day": "05-28-2021", "confirmations": 212672, "deaths": 5569, "recoveries": 0}, {"id": "148", "day": "05-29-2021", "confirmations": 212672, "deaths": 5569, "recoveries": 0}, {"id": "149", "day": "05-30-2021", "confirmations": 212702, "deaths": 5569, "recoveries": 0}, {"id": "150", "day": "05-31-2021", "confirmations": 212702, "deaths": 5569, "recoveries": 0}, {"id": "151", "day": "06-01-2021", "confirmations": 212796, "deaths": 5569, "recoveries": 0}, {"id": "152", "day": "06-02-2021", "confirmations": 212879, "deaths": 5569, "recoveries": 0}, {"id": "153", "day": "06-03-2021", "confirmations": 212928, "deaths": 5569, "recoveries": 0}, {"id": "154", "day": "06-04-2021", "confirmations": 212999, "deaths": 5569, "recoveries": 0}, {"id": "155", "day": "06-05-2021", "confirmations": 212999, "deaths": 5569, "recoveries": 0}, {"id": "156", "day": "06-06-2021", "confirmations": 213091, "deaths": 5569, "recoveries": 0}, {"id": "157", "day": "06-07-2021", "confirmations": 213166, "deaths": 5570, "recoveries": 0}, {"id": "158", "day": "06-08-2021", "confirmations": 213188, "deaths": 5570, "recoveries": 0}, {"id": "159", "day": "06-09-2021", "confirmations": 213411, "deaths": 5570, "recoveries": 0}, {"id": "160", "day": "06-10-2021", "confirmations": 213524, "deaths": 5571, "recoveries": 0}, {"id": "161", "day": "06-11-2021", "confirmations": 213642, "deaths": 5571, "recoveries": 0}, {"id": "162", "day": "06-12-2021", "confirmations": 213642, "deaths": 5571, "recoveries": 0}, {"id": "163", "day": "06-13-2021", "confirmations": 213757, "deaths": 5572, "recoveries": 0}, {"id": "164", "day": "06-14-2021", "confirmations": 214004, "deaths": 5572, "recoveries": 0}, {"id": "165", "day": "06-15-2021", "confirmations": 214102, "deaths": 5572, "recoveries": 0}, {"id": "166", "day": "06-16-2021", "confirmations": 214243, "deaths": 5572, "recoveries": 0}, {"id": "167", "day": "06-17-2021", "confirmations": 214382, "deaths": 5572, "recoveries": 0}, {"id": "168", "day": "06-18-2021", "confirmations": 214545, "deaths": 5572, "recoveries": 0}, {"id": "169", "day": "06-19-2021", "confirmations": 214545, "deaths": 5572, "recoveries": 0}, {"id": "170", "day": "06-20-2021", "confirmations": 214721, "deaths": 5572, "recoveries": 0}, {"id": "171", "day": "06-21-2021", "confirmations": 215205, "deaths": 5572, "recoveries": 0}, {"id": "172", "day": "06-22-2021", "confirmations": 215380, "deaths": 5572, "recoveries": 0}, {"id": "173", "day": "06-23-2021", "confirmations": 215593, "deaths": 5573, "recoveries": 0}, {"id": "174", "day": "06-24-2021", "confirmations": 216030, "deaths": 5573, "recoveries": 0}, {"id": "175", "day": "06-25-2021", "confirmations": 216366, "deaths": 5574, "recoveries": 0}, {"id": "176", "day": "06-26-2021", "confirmations": 216366, "deaths": 5574, "recoveries": 0}, {"id": "177", "day": "06-27-2021", "confirmations": 216782, "deaths": 5575, "recoveries": 0}, {"id": "178", "day": "06-28-2021", "confirmations": 217452, "deaths": 5575, "recoveries": 0}, {"id": "179", "day": "06-29-2021", "confirmations": 217732, "deaths": 5575, "recoveries": 0}, {"id": "180", "day": "06-30-2021", "confirmations": 218245, "deaths": 5575, "recoveries": 0}, {"id": "181", "day": "07-01-2021", "confirmations": 218726, "deaths": 5575, "recoveries": 0}, {"id": "182", "day": "07-02-2021", "confirmations": 219296, "deaths": 5575, "recoveries": 0}, {"id": "183", "day": "07-03-2021", "confirmations": 219296, "deaths": 5575, "recoveries": 0}, {"id": "184", "day": "07-04-2021", "confirmations": 219831, "deaths": 5575, "recoveries": 0}, {"id": "185", "day": "07-05-2021", "confirmations": 221087, "deaths": 5577, "recoveries": 0}, {"id": "186", "day": "07-06-2021", "confirmations": 221785, "deaths": 5578, "recoveries": 0}, {"id": "187", "day": "07-07-2021", "confirmations": 222448, "deaths": 5578, "recoveries": 0}, {"id": "188", "day": "07-08-2021", "confirmations": 223149, "deaths": 5578, "recoveries": 0}, {"id": "189", "day": "07-09-2021", "confirmations": 223804, "deaths": 5579, "recoveries": 0}, {"id": "190", "day": "07-10-2021", "confirmations": 223804, "deaths": 5579, "recoveries": 0}, {"id": "191", "day": "07-11-2021", "confirmations": 224501, "deaths": 5579, "recoveries": 0}, {"id": "192", "day": "07-12-2021", "confirmations": 225691, "deaths": 5579, "recoveries": 0}, {"id": "193", "day": "07-13-2021", "confirmations": 226428, "deaths": 5580, "recoveries": 0}, {"id": "194", "day": "07-14-2021", "confirmations": 227563, "deaths": 5581, "recoveries": 0}, {"id": "195", "day": "07-15-2021", "confirmations": 228424, "deaths": 5581, "recoveries": 0}, {"id": "196", "day": "07-16-2021", "confirmations": 229507, "deaths": 5583, "recoveries": 0}, {"id": "197", "day": "07-17-2021", "confirmations": 229507, "deaths": 5583, "recoveries": 0}, {"id": "198", "day": "07-18-2021", "confirmations": 230619, "deaths": 5586, "recoveries": 0}, {"id": "199", "day": "07-19-2021", "confirmations": 232672, "deaths": 5589, "recoveries": 0}, {"id": "200", "day": "07-20-2021", "confirmations": 233227, "deaths": 5589, "recoveries": 0}, {"id": "201", "day": "07-21-2021", "confirmations": 234168, "deaths": 5590, "recoveries": 0}, {"id": "202", "day": "07-22-2021", "confirmations": 234880, "deaths": 5594, "recoveries": 0}, {"id": "203", "day": "07-23-2021", "confirmations": 235635, "deaths": 5595, "recoveries": 0}, {"id": "204", "day": "07-24-2021", "confirmations": 235635, "deaths": 5595, "recoveries": 0}, {"id": "205", "day": "07-25-2021", "confirmations": 236873, "deaths": 5595, "recoveries": 0}, {"id": "206", "day": "07-26-2021", "confirmations": 238003, "deaths": 5597, "recoveries": 0}, {"id": "207", "day": "07-27-2021", "confirmations": 238707, "deaths": 5597, "recoveries": 0}, {"id": "208", "day": "07-28-2021", "confirmations": 239295, "deaths": 5603, "recoveries": 0}, {"id": "209", "day": "07-29-2021", "confirmations": 240019, "deaths": 5606, "recoveries": 0}, {"id": "210", "day": "07-30-2021", "confirmations": 240843, "deaths": 5610, "recoveries": 0}, {"id": "211", "day": "07-31-2021", "confirmations": 240843, "deaths": 5610, "recoveries": 0}, {"id": "212", "day": "08-01-2021", "confirmations": 241562, "deaths": 5615, "recoveries": 0}, {"id": "213", "day": "08-02-2021", "confirmations": 242668, "deaths": 5616, "recoveries": 0}, {"id": "214", "day": "08-03-2021", "confirmations": 243249, "deaths": 5616, "recoveries": 0}, {"id": "215", "day": "08-04-2021", "confirmations": 243857, "deaths": 5620, "recoveries": 0}, {"id": "216", "day": "08-05-2021", "confirmations": 244538, "deaths": 5623, "recoveries": 0}, {"id": "217", "day": "08-06-2021", "confirmations": 245341, "deaths": 5623, "recoveries": 0}, {"id": "218", "day": "08-07-2021", "confirmations": 245341, "deaths": 5623, "recoveries": 0}, {"id": "219", "day": "08-08-2021", "confirmations": 246205, "deaths": 5626, "recoveries": 0}, {"id": "220", "day": "08-09-2021", "confirmations": 247569, "deaths": 5629, "recoveries": 0}, {"id": "221", "day": "08-10-2021", "confirmations": 248112, "deaths": 5630, "recoveries": 0}, {"id": "222", "day": "08-11-2021", "confirmations": 248112, "deaths": 5630, "recoveries": 0}, {"id": "223", "day": "08-12-2021", "confirmations": 249958, "deaths": 5632, "recoveries": 0}, {"id": "224", "day": "08-13-2021", "confirmations": 251048, "deaths": 5634, "recoveries": 0}, {"id": "225", "day": "08-14-2021", "confirmations": 251048, "deaths": 5634, "recoveries": 0}, {"id": "226", "day": "08-15-2021", "confirmations": 252147, "deaths": 5638, "recoveries": 0}, {"id": "227", "day": "08-16-2021", "confirmations": 254541, "deaths": 5641, "recoveries": 0}, {"id": "228", "day": "08-17-2021", "confirmations": 255302, "deaths": 5641, "recoveries": 0}, {"id": "229", "day": "08-18-2021", "confirmations": 256675, "deaths": 5645, "recoveries": 0}, {"id": "230", "day": "08-19-2021", "confirmations": 258155, "deaths": 5647, "recoveries": 0}, {"id": "231", "day": "08-20-2021", "confirmations": 259883, "deaths": 5651, "recoveries": 0}, {"id": "232", "day": "08-21-2021", "confirmations": 259883, "deaths": 5651, "recoveries": 0}, {"id": "233", "day": "08-22-2021", "confirmations": 261509, "deaths": 5656, "recoveries": 0}, {"id": "234", "day": "08-23-2021", "confirmations": 264756, "deaths": 5658, "recoveries": 0}, {"id": "235", "day": "08-24-2021", "confirmations": 266149, "deaths": 5658, "recoveries": 0}, {"id": "236", "day": "08-25-2021", "confirmations": 267854, "deaths": 5662, "recoveries": 0}, {"id": "237", "day": "08-26-2021", "confirmations": 270243, "deaths": 5663, "recoveries": 0}, {"id": "238", "day": "08-27-2021", "confirmations": 272034, "deaths": 5668, "recoveries": 0}, {"id": "239", "day": "08-28-2021", "confirmations": 272034, "deaths": 5668, "recoveries": 0}, {"id": "240", "day": "08-29-2021", "confirmations": 274390, "deaths": 5671, "recoveries": 0}, {"id": "241", "day": "08-30-2021", "confirmations": 274390, "deaths": 5671, "recoveries": 0}, {"id": "242", "day": "08-31-2021", "confirmations": 278262, "deaths": 5672, "recoveries": 0}, {"id": "243", "day": "09-01-2021", "confirmations": 281590, "deaths": 5677, "recoveries": 0}, {"id": "244", "day": "09-02-2021", "confirmations": 283865, "deaths": 5682, "recoveries": 0}, {"id": "245", "day": "09-03-2021", "confirmations": 286256, "deaths": 5688, "recoveries": 0}, {"id": "246", "day": "09-04-2021", "confirmations": 286256, "deaths": 5688, "recoveries": 0}, {"id": "247", "day": "09-05-2021", "confirmations": 288645, "deaths": 5691, "recoveries": 0}, {"id": "248", "day": "09-06-2021", "confirmations": 293806, "deaths": 5699, "recoveries": 0}, {"id": "249", "day": "09-07-2021", "confirmations": 296310, "deaths": 5702, "recoveries": 0}, {"id": "250", "day": "09-08-2021", "confirmations": 298979, "deaths": 5712, "recoveries": 0}, {"id": "251", "day": "09-09-2021", "confirmations": 301276, "deaths": 5721, "recoveries": 0}, {"id": "252", "day": "09-10-2021", "confirmations": 303743, "deaths": 5726, "recoveries": 0}, {"id": "253", "day": "09-11-2021", "confirmations": 303743, "deaths": 5726, "recoveries": 0}, {"id": "254", "day": "09-12-2021", "confirmations": 306060, "deaths": 5734, "recoveries": 0}, {"id": "255", "day": "09-13-2021", "confirmations": 310368, "deaths": 5755, "recoveries": 0}, {"id": "256", "day": "09-14-2021", "confirmations": 312292, "deaths": 5760, "recoveries": 0}, {"id": "257", "day": "09-15-2021", "confirmations": 314590, "deaths": 5770, "recoveries": 0}, {"id": "258", "day": "09-16-2021", "confirmations": 317481, "deaths": 5774, "recoveries": 0}, {"id": "259", "day": "09-17-2021", "confirmations": 320099, "deaths": 5782, "recoveries": 0}, {"id": "260", "day": "09-18-2021", "confirmations": 320099, "deaths": 5782, "recoveries": 0}, {"id": "261", "day": "09-19-2021", "confirmations": 322816, "deaths": 5797, "recoveries": 0}, {"id": "262", "day": "09-20-2021", "confirmations": 328074, "deaths": 5814, "recoveries": 0}, {"id": "263", "day": "09-21-2021", "confirmations": 330650, "deaths": 5821, "recoveries": 0}, {"id": "264", "day": "09-22-2021", "confirmations": 333135, "deaths": 5831, "recoveries": 0}, {"id": "265", "day": "09-23-2021", "confirmations": 335611, "deaths": 5837, "recoveries": 0}, {"id": "266", "day": "09-24-2021", "confirmations": 338338, "deaths": 5839, "recoveries": 0}, {"id": "267", "day": "09-25-2021", "confirmations": 338338, "deaths": 5839, "recoveries": 0}, {"id": "268", "day": "09-26-2021", "confirmations": 341641, "deaths": 5852, "recoveries": 0}, {"id": "269", "day": "09-27-2021", "confirmations": 347300, "deaths": 5864, "recoveries": 0}, {"id": "270", "day": "09-28-2021", "confirmations": 349570, "deaths": 5870, "recoveries": 0}, {"id": "271", "day": "09-29-2021", "confirmations": 352939, "deaths": 5879, "recoveries": 0}, {"id": "272", "day": "09-30-2021", "confirmations": 355542, "deaths": 5892, "recoveries": 0}, {"id": "273", "day": "10-01-2021", "confirmations": 358550, "deaths": 5897, "recoveries": 0}, {"id": "274", "day": "10-02-2021", "confirmations": 358550, "deaths": 5897, "recoveries": 0}, {"id": "275", "day": "10-03-2021", "confirmations": 360881, "deaths": 5907, "recoveries": 0}, {"id": "276", "day": "10-04-2021", "confirmations": 364866, "deaths": 5924, "recoveries": 0}, {"id": "277", "day": "10-05-2021", "confirmations": 366624, "deaths": 5926, "recoveries": 0}, {"id": "278", "day": "10-06-2021", "confirmations": 368629, "deaths": 5934, "recoveries": 0}, {"id": "279", "day": "10-07-2021", "confirmations": 372029, "deaths": 5942, "recoveries": 0}, {"id": "280", "day": "10-08-2021", "confirmations": 372029, "deaths": 5942, "recoveries": 0}, {"id": "281", "day": "10-09-2021", "confirmations": 377734, "deaths": 5965, "recoveries": 0}, {"id": "282", "day": "10-10-2021", "confirmations": 377734, "deaths": 5965, "recoveries": 0}, {"id": "283", "day": "10-11-2021", "confirmations": 382203, "deaths": 5973, "recoveries": 0}, {"id": "284", "day": "10-12-2021", "confirmations": 384250, "deaths": 5974, "recoveries": 0}, {"id": "285", "day": "10-13-2021", "confirmations": 386516, "deaths": 5978, "recoveries": 0}, {"id": "286", "day": "10-14-2021", "confirmations": 389152, "deaths": 5990, "recoveries": 0}, {"id": "287", "day": "10-15-2021", "confirmations": 392282, "deaths": 6005, "recoveries": 0}, {"id": "288", "day": "10-16-2021", "confirmations": 392282, "deaths": 6005, "recoveries": 0}, {"id": "289", "day": "10-17-2021", "confirmations": 395247, "deaths": 6015, "recoveries": 0}, {"id": "290", "day": "10-18-2021", "confirmations": 401644, "deaths": 6035, "recoveries": 0}, {"id": "291", "day": "10-19-2021", "confirmations": 404844, "deaths": 6037, "recoveries": 0}, {"id": "292", "day": "10-20-2021", "confirmations": 408294, "deaths": 6050, "recoveries": 0}, {"id": "293", "day": "10-21-2021", "confirmations": 412534, "deaths": 6063, "recoveries": 0}, {"id": "294", "day": "10-22-2021", "confirmations": 415829, "deaths": 6074, "recoveries": 0}, {"id": "295", "day": "10-23-2021", "confirmations": 415829, "deaths": 6074, "recoveries": 0}, {"id": "296", "day": "10-24-2021", "confirmations": 418980, "deaths": 6086, "recoveries": 0}, {"id": "297", "day": "10-25-2021", "confirmations": 418980, "deaths": 6086, "recoveries": 0}, {"id": "298", "day": "10-26-2021", "confirmations": 427150, "deaths": 6117, "recoveries": 0}, {"id": "299", "day": "10-27-2021", "confirmations": 429731, "deaths": 6122, "recoveries": 0}, {"id": "300", "day": "10-28-2021", "confirmations": 432395, "deaths": 6134, "recoveries": 0}, {"id": "301", "day": "10-29-2021", "confirmations": 434956, "deaths": 6141, "recoveries": 0}, {"id": "302", "day": "10-30-2021", "confirmations": 434956, "deaths": 6141, "recoveries": 0}, {"id": "303", "day": "10-31-2021", "confirmations": 437972, "deaths": 6150, "recoveries": 0}, {"id": "304", "day": "11-01-2021", "confirmations": 442953, "deaths": 6167, "recoveries": 0}, {"id": "305", "day": "11-02-2021", "confirmations": 445163, "deaths": 6177, "recoveries": 0}, {"id": "306", "day": "11-03-2021", "confirmations": 447655, "deaths": 6184, "recoveries": 0}, {"id": "307", "day": "11-04-2021", "confirmations": 450455, "deaths": 6201, "recoveries": 0}, {"id": "308", "day": "11-05-2021", "confirmations": 452440, "deaths": 6214, "recoveries": 0}, {"id": "309", "day": "11-06-2021", "confirmations": 452440, "deaths": 6214, "recoveries": 0}, {"id": "310", "day": "11-07-2021", "confirmations": 455023, "deaths": 6223, "recoveries": 0}, {"id": "311", "day": "11-08-2021", "confirmations": 459325, "deaths": 6237, "recoveries": 0}, {"id": "312", "day": "11-09-2021", "confirmations": 461109, "deaths": 6242, "recoveries": 0}, {"id": "313", "day": "11-10-2021", "confirmations": 463279, "deaths": 6260, "recoveries": 0}, {"id": "314", "day": "11-11-2021", "confirmations": 465413, "deaths": 6272, "recoveries": 0}, {"id": "315", "day": "11-12-2021", "confirmations": 468197, "deaths": 6276, "recoveries": 0}, {"id": "316", "day": "11-13-2021", "confirmations": 468197, "deaths": 6276, "recoveries": 0}, {"id": "317", "day": "11-14-2021", "confirmations": 470856, "deaths": 6282, "recoveries": 0}, {"id": "318", "day": "11-15-2021", "confirmations": 475375, "deaths": 6295, "recoveries": 0}, {"id": "319", "day": "11-16-2021", "confirmations": 477295, "deaths": 6297, "recoveries": 0}, {"id": "320", "day": "11-17-2021", "confirmations": 479712, "deaths": 6314, "recoveries": 0}, {"id": "321", "day": "11-18-2021", "confirmations": 482288, "deaths": 6334, "recoveries": 0}, {"id": "322", "day": "11-19-2021", "confirmations": 484744, "deaths": 6342, "recoveries": 0}, {"id": "323", "day": "11-20-2021", "confirmations": 484744, "deaths": 6342, "recoveries": 0}, {"id": "324", "day": "11-21-2021", "confirmations": 487152, "deaths": 6349, "recoveries": 0}, {"id": "325", "day": "11-22-2021", "confirmations": 491640, "deaths": 6357, "recoveries": 0}, {"id": "326", "day": "11-23-2021", "confirmations": 493571, "deaths": 6361, "recoveries": 0}, {"id": "327", "day": "11-24-2021", "confirmations": 495724, "deaths": 6368, "recoveries": 0}, {"id": "328", "day": "11-25-2021", "confirmations": 498101, "deaths": 6377, "recoveries": 0}, {"id": "329", "day": "11-26-2021", "confirmations": 501028, "deaths": 6382, "recoveries": 0}, {"id": "330", "day": "11-27-2021", "confirmations": 501028, "deaths": 6382, "recoveries": 0}, {"id": "331", "day": "11-28-2021", "confirmations": 502991, "deaths": 6391, "recoveries": 0}, {"id": "332", "day": "11-29-2021", "confirmations": 506960, "deaths": 6401, "recoveries": 0}, {"id": "333", "day": "11-30-2021", "confirmations": 508932, "deaths": 6405, "recoveries": 0}, {"id": "334", "day": "12-01-2021", "confirmations": 510999, "deaths": 6412, "recoveries": 0}, {"id": "335", "day": "12-02-2021", "confirmations": 513790, "deaths": 6420, "recoveries": 0}, {"id": "336", "day": "12-03-2021", "confirmations": 516146, "deaths": 6428, "recoveries": 0}, {"id": "337", "day": "12-04-2021", "confirmations": 516146, "deaths": 6428, "recoveries": 0}, {"id": "338", "day": "12-05-2021", "confirmations": 518713, "deaths": 6433, "recoveries": 0}, {"id": "339", "day": "12-06-2021", "confirmations": 523118, "deaths": 6439, "recoveries": 0}, {"id": "340", "day": "12-07-2021", "confirmations": 525225, "deaths": 6441, "recoveries": 0}, {"id": "341", "day": "12-08-2021", "confirmations": 527538, "deaths": 6452, "recoveries": 0}, {"id": "342", "day": "12-09-2021", "confirmations": 529840, "deaths": 6467, "recoveries": 0}, {"id": "343", "day": "12-10-2021", "confirmations": 532302, "deaths": 6476, "recoveries": 0}, {"id": "344", "day": "12-11-2021", "confirmations": 532302, "deaths": 6476, "recoveries": 0}, {"id": "345", "day": "12-12-2021", "confirmations": 534893, "deaths": 6481, "recoveries": 0}, {"id": "346", "day": "12-13-2021", "confirmations": 539435, "deaths": 6489, "recoveries": 0}, {"id": "347", "day": "12-14-2021", "confirmations": 541254, "deaths": 6491, "recoveries": 0}, {"id": "348", "day": "12-15-2021", "confirmations": 543685, "deaths": 6501, "recoveries": 0}, {"id": "349", "day": "12-16-2021", "confirmations": 546573, "deaths": 6501, "recoveries": 0}, {"id": "350", "day": "12-17-2021", "confirmations": 549702, "deaths": 6504, "recoveries": 0}, {"id": "351", "day": "12-18-2021", "confirmations": 549702, "deaths": 6504, "recoveries": 0}, {"id": "352", "day": "12-19-2021", "confirmations": 553163, "deaths": 6508, "recoveries": 0}, {"id": "353", "day": "12-20-2021", "confirmations": 559959, "deaths": 6516, "recoveries": 0}, {"id": "354", "day": "12-21-2021", "confirmations": 562333, "deaths": 6522, "recoveries": 0}, {"id": "355", "day": "12-22-2021", "confirmations": 566995, "deaths": 6525, "recoveries": 0}, {"id": "356", "day": "12-23-2021", "confirmations": 570288, "deaths": 6535, "recoveries": 0}, {"id": "357", "day": "12-24-2021", "confirmations": 577043, "deaths": 6545, "recoveries": 0}, {"id": "358", "day": "12-25-2021", "confirmations": 577043, "deaths": 6545, "recoveries": 0}, {"id": "359", "day": "12-26-2021", "confirmations": 582378, "deaths": 6548, "recoveries": 0}, {"id": "360", "day": "12-27-2021", "confirmations": 582378, "deaths": 6548, "recoveries": 0}, {"id": "361", "day": "12-28-2021", "confirmations": 594753, "deaths": 6551, "recoveries": 0}, {"id": "362", "day": "12-29-2021", "confirmations": 600682, "deaths": 6553, "recoveries": 0}, {"id": "363", "day": "12-30-2021", "confirmations": 621732, "deaths": 6556, "recoveries": 0}, {"id": "364", "day": "12-31-2021", "confirmations": 632125, "deaths": 6567, "recoveries": 0}, {"id": "365", "day": "01-01-2022", "confirmations": 632125, "deaths": 6567, "recoveries": 0}, {"id": "366", "day": "01-02-2022", "confirmations": 646159, "deaths": 6581, "recoveries": 0}, {"id": "367", "day": "01-03-2022", "confirmations": 646159, "deaths": 6581, "recoveries": 0}, {"id": "368", "day": "01-04-2022", "confirmations": 668473, "deaths": 6589, "recoveries": 0}, {"id": "369", "day": "01-05-2022", "confirmations": 689750, "deaths": 6599, "recoveries": 0}, {"id": "370", "day": "01-06-2022", "confirmations": 698962, "deaths": 6605, "recoveries": 0}, {"id": "371", "day": "01-07-2022", "confirmations": 706873, "deaths": 6626, "recoveries": 0}, {"id": "372", "day": "01-08-2022", "confirmations": 706873, "deaths": 6626, "recoveries": 0}, {"id": "373", "day": "01-09-2022", "confirmations": 715796, "deaths": 6634, "recoveries": 0}]}